rtl/saturation_guard.v
//============================================================================
// Module:      saturation_guard
// Description: Combinational output saturation / clamping with anti-windup
//              integrator hold signal. When the raw PID output exceeds the
//              configured limits, the output is clamped and integrator_hold
//              is asserted to prevent integral windup.
//
// Fixed-Point: Signed Q8.8 — 16-bit, 1 sign + 7 integer + 8 fractional
//============================================================================

module saturation_guard #(
    parameter signed [15:0] MAX_OUT = 16'h7F00,  // +127.0 in Q8.8
    parameter signed [15:0] MIN_OUT = 16'h8100   // -127.0 in Q8.8
)(
    input  wire [15:0] raw_in,          // Raw PID output (Q8.8 signed)
    output wire [15:0] clamped_out,     // Clamped output (Q8.8 signed)
    output wire        integrator_hold  // High when output is saturated
);

    // Saturation logic (purely combinational)
    wire saturated_high = ($signed(raw_in) > $signed(MAX_OUT));
    wire saturated_low  = ($signed(raw_in) < $signed(MIN_OUT));

    assign clamped_out = saturated_high ? MAX_OUT :
                         saturated_low  ? MIN_OUT :
                         raw_in;

    // Assert integrator hold when output is at either limit
    assign integrator_hold = saturated_high | saturated_low;

endmodule

rtl/pid_controller.v
//============================================================================
// Module:      pid_controller
// Description: Parameterized PID controller using signed Q8.8 fixed-point
//              arithmetic. Implements Proportional, Integral, and Derivative
//              control with anti-windup support via integrator_hold.
//
// Fixed-Point: Signed Q8.8 — 1 sign bit, 7 integer bits, 8 fractional bits
//              Range: -128.0 to +127.99609375
//              Resolution: 1/256 ≈ 0.00390625
//============================================================================

module pid_controller #(
    parameter signed [15:0] MAX_OUT = 16'h7F00,  // +127.0 in Q8.8
    parameter signed [15:0] MIN_OUT = 16'h8100   // -127.0 in Q8.8
)(
    input  wire        clk,
    input  wire        rst,
    // Runtime-configurable PID gains (Q8.8 signed)
    input  wire [15:0] Kp,               // Proportional gain
    input  wire [15:0] Ki,               // Integral gain
    input  wire [15:0] Kd,               // Derivative gain
    input  wire [15:0] error_in,         // Signed Q8.8 error
    input  wire        integrator_hold,  // Freeze integrator when saturated
    output reg  [15:0] pid_out           // Signed Q8.8 PID output (raw, unclamped)
);

    // Internal registers
    reg signed [15:0] prev_error;       // Previous error for derivative term
    reg signed [31:0] integrator;       // Wider accumulator for integral term

    // Intermediate wires for combinational arithmetic
    wire signed [15:0] error_signed = $signed(error_in);

    // --- Proportional term ---
    // Q8.8 × Q8.8 = Q16.16 (32 bits). Extract [23:8] for Q8.8 result.
    wire signed [31:0] p_product = $signed(Kp) * error_signed;
    wire signed [15:0] p_term;
    assign p_term = saturate_q88(p_product);

    // --- Derivative term ---
    wire signed [15:0] error_diff = error_signed - prev_error;
    wire signed [31:0] d_product  = $signed(Kd) * error_diff;
    wire signed [15:0] d_term;
    assign d_term = saturate_q88(d_product);

    // --- Integral term (Ki × error, to be accumulated) ---
    wire signed [31:0] i_product = $signed(Ki) * error_signed;
    wire signed [15:0] i_increment;
    assign i_increment = saturate_q88(i_product);

    // --- Integrator value clamped to Q8.8 range for output ---
    wire signed [15:0] i_term;
    assign i_term = clamp_integrator(integrator);

    // --- PID sum (use wider bus to detect overflow before clamping) ---
    wire signed [31:0] pid_sum_wide = $signed(p_term) + $signed(i_term) + $signed(d_term);
    wire signed [15:0] pid_sum_clamped;
    assign pid_sum_clamped = clamp_to_range(pid_sum_wide, $signed(MAX_OUT), $signed(MIN_OUT));

    // Clocked process
    always @(posedge clk) begin
        if (rst) begin
            prev_error  <= 16'sd0;
            integrator  <= 32'sd0;
            pid_out     <= 16'sd0;
        end else begin
            // Update previous error
            prev_error <= error_signed;

            // Update integrator (with anti-windup hold)
            if (!integrator_hold) begin
                integrator <= integrator + $signed({{16{i_increment[15]}}, i_increment});
            end

            // Output the clamped PID sum
            pid_out <= pid_sum_clamped;
        end
    end

    // Function: saturate_q88
    // Extracts Q8.8 from a Q16.16 product with overflow saturation.
    function signed [15:0] saturate_q88;
        input signed [31:0] product;
        reg signed [15:0] truncated;
        reg overflow_pos, overflow_neg;
        begin
            truncated    = product[23:8];
            // Check if upper bits [31:23] are all 0 (positive) or all 1 (negative)
            // For no overflow: positive → [31:23] == 9'b0, negative → [31:23] == 9'h1FF
            overflow_pos = (product[31] == 1'b0) && (product[31:23] != 9'h000);
            overflow_neg = (product[31] == 1'b1) && (product[31:23] != 9'h1FF);

            if (overflow_pos)
                saturate_q88 = 16'h7FFF;  // Max positive Q8.8
            else if (overflow_neg)
                saturate_q88 = 16'h8000;  // Max negative Q8.8
            else
                saturate_q88 = truncated;
        end
    endfunction

    // Function: clamp_integrator
    // Clamps the 32-bit integrator accumulator to Q8.8 range.
    function signed [15:0] clamp_integrator;
        input signed [31:0] acc;
        begin
            if (acc > $signed(32'h00007FFF))
                clamp_integrator = 16'h7FFF;
            else if (acc < $signed(32'hFFFF8000))
                clamp_integrator = 16'h8000;
            else
                clamp_integrator = acc[15:0];
        end
    endfunction

    // Function: clamp_to_range
    // Clamps a wide sum to the specified [MIN, MAX] range.
    function signed [15:0] clamp_to_range;
        input signed [31:0] val;
        input signed [15:0] max_val;
        input signed [15:0] min_val;
        begin
            if (val > $signed({{16{max_val[15]}}, max_val}))
                clamp_to_range = max_val;
            else if (val < $signed({{16{min_val[15]}}, min_val}))
                clamp_to_range = min_val;
            else
                clamp_to_range = val[15:0];
        end
    endfunction

endmodule

sim/tb_pid.v
//============================================================================
// Testbench: tb_pid
// Description: Standalone Verilog testbench for pid_controller and
//              saturation_guard modules. Applies a step error input and
//              observes the PID response over 500 clock cycles.
//
//              Updated for runtime gain inputs: Kp/Ki/Kd are now driven
//              as reg signals rather than compile-time parameters.
//
// Run with Icarus Verilog:
//   iverilog -o tb_pid rtl/pid_controller.v rtl/saturation_guard.v sim/tb_pid.v
//   vvp tb_pid
//   gtkwave tb_pid.vcd  (optional waveform viewer)
//============================================================================

`timescale 1ns / 1ps

module tb_pid;

    //------------------------------------------------------------------------
    // Gain values — driven as runtime signals
    //------------------------------------------------------------------------
    localparam signed [15:0] KP_VAL  = 16'h0100;  // 1.0
    localparam signed [15:0] KI_VAL  = 16'h001A;  // ~0.1 (26/256)
    localparam signed [15:0] KD_VAL  = 16'h0080;  // 0.5
    localparam signed [15:0] MAX_OUT = 16'h7F00;  // +127.0
    localparam signed [15:0] MIN_OUT = 16'h8100;  // -127.0

    //------------------------------------------------------------------------
    // DUT signals
    //------------------------------------------------------------------------
    reg         clk;
    reg         rst;
    reg  [15:0] error_in;
    reg  [15:0] kp_reg;
    reg  [15:0] ki_reg;
    reg  [15:0] kd_reg;

    wire [15:0] pid_raw_out;
    wire [15:0] pid_clamped_out;
    wire        integrator_hold;

    //------------------------------------------------------------------------
    // DUT instantiation: PID → Saturation Guard
    //------------------------------------------------------------------------
    pid_controller #(
        .MAX_OUT (MAX_OUT),
        .MIN_OUT (MIN_OUT)
    ) dut_pid (
        .clk             (clk),
        .rst             (rst),
        .Kp              (kp_reg),
        .Ki              (ki_reg),
        .Kd              (kd_reg),
        .error_in        (error_in),
        .integrator_hold (integrator_hold),
        .pid_out         (pid_raw_out)
    );

    saturation_guard #(
        .MAX_OUT (MAX_OUT),
        .MIN_OUT (MIN_OUT)
    ) dut_sat (
        .raw_in          (pid_raw_out),
        .clamped_out     (pid_clamped_out),
        .integrator_hold (integrator_hold)
    );

    //------------------------------------------------------------------------
    // Clock generation — 20 ns period (50 MHz)
    //------------------------------------------------------------------------
    initial clk = 0;
    always #10 clk = ~clk;

    //------------------------------------------------------------------------
    // Helper function: Convert Q8.8 to real for display
    //------------------------------------------------------------------------
    // Note: Icarus Verilog supports $itor for integer-to-real conversion
    function real q88_to_real;
        input [15:0] val;
        reg signed [15:0] sval;
        begin
            sval = val;
            q88_to_real = $itor(sval) / 256.0;
        end
    endfunction

    //------------------------------------------------------------------------
    // VCD dump setup
    //------------------------------------------------------------------------
    initial begin
        $dumpfile("tb_pid.vcd");
        $dumpvars(0, tb_pid);
    end

    //------------------------------------------------------------------------
    // Test sequence
    //------------------------------------------------------------------------
    integer cycle;

    initial begin
        $display("============================================================");
        $display("  PID Controller + Saturation Guard Testbench");
        $display("  Kp=%.4f  Ki=%.4f  Kd=%.4f", q88_to_real(KP_VAL), q88_to_real(KI_VAL), q88_to_real(KD_VAL));
        $display("============================================================");
        $display("");
        $display("  Cycle | Error(Q8.8) | Error(dec) | PID Raw    | PID Clamp  | Hold");
        $display("  ------|-------------|------------|------------|------------|-----");

        // Initialize
        rst      = 1;
        error_in = 16'h0000;
        kp_reg   = KP_VAL;
        ki_reg   = KI_VAL;
        kd_reg   = KD_VAL;
        cycle    = 0;

        // Hold reset for 5 cycles
        repeat (5) @(posedge clk);
        rst = 0;

        // ---- TEST 1: Positive step error (+10.0 in Q8.8 = 0x0A00) ----
        $display("");
        $display("  [TEST 1] Step error: +10.0 (0x0A00)");
        error_in = 16'h0A00;  // +10.0

        repeat (100) begin
            @(posedge clk);
            cycle = cycle + 1;
            if (cycle <= 20 || cycle % 10 == 0) begin
                $display("  %5d | 0x%04h     | %8.4f   | 0x%04h     | 0x%04h     | %b",
                    cycle, error_in, q88_to_real(error_in),
                    pid_raw_out, pid_clamped_out, integrator_hold);
            end
        end

        // ---- TEST 2: Zero error (should see derivative kick, integral hold) ----
        $display("");
        $display("  [TEST 2] Step error to 0.0 (0x0000)");
        error_in = 16'h0000;

        repeat (100) begin
            @(posedge clk);
            cycle = cycle + 1;
            if (cycle <= 120 || cycle % 10 == 0) begin
                $display("  %5d | 0x%04h     | %8.4f   | 0x%04h     | 0x%04h     | %b",
                    cycle, error_in, q88_to_real(error_in),
                    pid_raw_out, pid_clamped_out, integrator_hold);
            end
        end

        // ---- TEST 3: Negative step error (-5.0 = 0xFB00) ----
        $display("");
        $display("  [TEST 3] Step error: -5.0 (0xFB00)");
        error_in = 16'hFB00;  // -5.0

        repeat (100) begin
            @(posedge clk);
            cycle = cycle + 1;
            if (cycle <= 220 || cycle % 10 == 0) begin
                $display("  %5d | 0x%04h     | %8.4f   | 0x%04h     | 0x%04h     | %b",
                    cycle, error_in, q88_to_real(error_in),
                    pid_raw_out, pid_clamped_out, integrator_hold);
            end
        end

        // ---- TEST 4: Large error to test saturation (+120.0 = 0x7800) ----
        $display("");
        $display("  [TEST 4] Large error: +120.0 (0x7800) — should saturate");
        error_in = 16'h7800;  // +120.0

        repeat (50) begin
            @(posedge clk);
            cycle = cycle + 1;
            $display("  %5d | 0x%04h     | %8.4f   | 0x%04h     | 0x%04h     | %b",
                cycle, error_in, q88_to_real(error_in),
                pid_raw_out, pid_clamped_out, integrator_hold);
        end

        // ---- TEST 5: Runtime gain change ----
        $display("");
        $display("  [TEST 5] Runtime gain change: Kp 1.0 → 2.0, error=+10.0");
        error_in = 16'h0A00;  // +10.0
        kp_reg   = 16'h0200;  // 2.0 in Q8.8

        repeat (20) begin
            @(posedge clk);
            cycle = cycle + 1;
            $display("  %5d | 0x%04h     | %8.4f   | 0x%04h     | 0x%04h     | %b  (Kp=%.4f)",
                cycle, error_in, q88_to_real(error_in),
                pid_raw_out, pid_clamped_out, integrator_hold,
                q88_to_real(kp_reg));
        end

        // ---- TEST 6: Reset mid-operation ----
        $display("");
        $display("  [TEST 6] Assert reset — all outputs should zero");
        rst = 1;
        repeat (3) @(posedge clk);
        cycle = cycle + 3;
        $display("  %5d | 0x%04h     | %8.4f   | 0x%04h     | 0x%04h     | %b",
            cycle, error_in, q88_to_real(error_in),
            pid_raw_out, pid_clamped_out, integrator_hold);

        // Verify reset behavior
        if (pid_raw_out == 16'h0000 && pid_clamped_out == 16'h0000)
            $display("  [PASS] Reset cleared PID output correctly.");
        else
            $display("  [FAIL] PID output not zero after reset! raw=0x%04h clamp=0x%04h",
                pid_raw_out, pid_clamped_out);

        rst = 0;

        // ---- Summary ----
        $display("");
        $display("============================================================");
        $display("  Testbench complete. Review tb_pid.vcd for waveforms.");
        $display("============================================================");
        $finish;
    end

endmodule

tb_pid.vcd
$date
	Sun May 10 08:43:20 2026
$end
$version
	Icarus Verilog
$end
$timescale
	1ps
$end
$scope module tb_pid $end
$var wire 16 ! pid_raw_out [15:0] $end
$var wire 16 " pid_clamped_out [15:0] $end
$var wire 1 # integrator_hold $end
$var parameter 16 $ KD_VAL $end
$var parameter 16 % KI_VAL $end
$var parameter 16 & KP_VAL $end
$var parameter 16 ' MAX_OUT $end
$var parameter 16 ( MIN_OUT $end
$var reg 1 ) clk $end
$var reg 16 * error_in [15:0] $end
$var reg 16 + kd_reg [15:0] $end
$var reg 16 , ki_reg [15:0] $end
$var reg 16 - kp_reg [15:0] $end
$var reg 1 . rst $end
$var integer 32 / cycle [31:0] $end
$scope function q88_to_real $end
$var reg 16 0 sval [15:0] $end
$var reg 16 1 val [15:0] $end
$upscope $end
$scope module dut_pid $end
$var wire 16 2 Kd [15:0] $end
$var wire 16 3 Ki [15:0] $end
$var wire 16 4 Kp [15:0] $end
$var wire 1 ) clk $end
$var wire 16 5 error_in [15:0] $end
$var wire 16 6 error_signed [15:0] $end
$var wire 1 . rst $end
$var wire 32 7 pid_sum_wide [31:0] $end
$var wire 16 8 pid_sum_clamped [15:0] $end
$var wire 16 9 p_term [15:0] $end
$var wire 32 : p_product [31:0] $end
$var wire 1 # integrator_hold $end
$var wire 16 ; i_term [15:0] $end
$var wire 32 < i_product [31:0] $end
$var wire 16 = i_increment [15:0] $end
$var wire 16 > error_diff [15:0] $end
$var wire 16 ? d_term [15:0] $end
$var wire 32 @ d_product [31:0] $end
$var parameter 16 A MAX_OUT $end
$var parameter 16 B MIN_OUT $end
$var reg 32 C integrator [31:0] $end
$var reg 16 D pid_out [15:0] $end
$var reg 16 E prev_error [15:0] $end
$scope function clamp_integrator $end
$var reg 32 F acc [31:0] $end
$upscope $end
$scope function clamp_to_range $end
$var reg 16 G max_val [15:0] $end
$var reg 16 H min_val [15:0] $end
$var reg 32 I val [31:0] $end
$upscope $end
$scope function saturate_q88 $end
$var reg 1 J overflow_neg $end
$var reg 1 K overflow_pos $end
$var reg 32 L product [31:0] $end
$var reg 16 M truncated [15:0] $end
$upscope $end
$upscope $end
$scope module dut_sat $end
$var wire 1 # integrator_hold $end
$var wire 16 N raw_in [15:0] $end
$var wire 1 O saturated_low $end
$var wire 1 P saturated_high $end
$var wire 16 Q clamped_out [15:0] $end
$var parameter 16 R MAX_OUT $end
$var parameter 16 S MIN_OUT $end
$upscope $end
$upscope $end
$enddefinitions $end
$comment Show the parameter values. $end
$dumpall
b1000000100000000 S
b111111100000000 R
b1000000100000000 B
b111111100000000 A
b1000000100000000 (
b111111100000000 '
b100000000 &
b11010 %
b10000000 $
$end
#0
$dumpvars
bx Q
xP
xO
bx N
b0 M
b0 L
0K
0J
bx I
b1000000100000000 H
b111111100000000 G
bx F
bx E
bx D
bx C
bx @
bx ?
bx >
b0 =
b0 <
bx ;
b0 :
b0 9
bx 8
bx 7
b0 6
b0 5
b100000000 4
b11010 3
b10000000 2
b10000000 1
b10000000 0
b0 /
1.
b100000000 -
b11010 ,
b10000000 +
b0 *
0)
x#
bx "
bx !
$end
#10000
b0 8
b0 I
b0 "
b0 Q
0#
b0 7
b0 ;
b0 F
b0 ?
0P
0O
b0 !
b0 D
b0 N
b0 C
b0 @
b0 >
b0 E
1)
#20000
0)
#30000
1)
#40000
0)
#50000
1)
#60000
0)
#70000
1)
#80000
0)
#90000
b101000000000 E
b101000000000 8
b101000000000 I
b101000000000 9
b101000000000 7
b0 ?
b100000100 =
b0 M
b0 L
b10100000000000000000 :
b0 @
b0 >
b10000010000000000 <
b101000000000 *
b101000000000 5
b101000000000 6
0.
1)
#100000
0)
#110000
b101000000000 "
b101000000000 Q
b101100000100 8
b101100000100 I
b101100000100 7
b100000100 ;
b100000100 F
b101000000000 !
b101000000000 D
b101000000000 N
b100000100 C
b101000000000 0
b101000000000 1
b1 /
1)
#120000
0)
#130000
b101100000100 "
b101100000100 Q
b110000001000 8
b110000001000 I
b110000001000 7
b1000001000 ;
b1000001000 F
b101100000100 !
b101100000100 D
b101100000100 N
b1000001000 C
b10 /
1)
#140000
0)
#150000
b110000001000 "
b110000001000 Q
b110100001100 8
b110100001100 I
b110100001100 7
b1100001100 ;
b1100001100 F
b110000001000 !
b110000001000 D
b110000001000 N
b1100001100 C
b11 /
1)
#160000
0)
#170000
b110100001100 "
b110100001100 Q
b111000010000 8
b111000010000 I
b111000010000 7
b10000010000 ;
b10000010000 F
b110100001100 !
b110100001100 D
b110100001100 N
b10000010000 C
b100 /
1)
#180000
0)
#190000
b111000010000 "
b111000010000 Q
b111100010100 8
b111100010100 I
b111100010100 7
b10100010100 ;
b10100010100 F
b111000010000 !
b111000010000 D
b111000010000 N
b10100010100 C
b101 /
1)
#200000
0)
#210000
b111100010100 "
b111100010100 Q
b1000000011000 8
b1000000011000 I
b1000000011000 7
b11000011000 ;
b11000011000 F
b111100010100 !
b111100010100 D
b111100010100 N
b11000011000 C
b110 /
1)
#220000
0)
#230000
b1000000011000 "
b1000000011000 Q
b1000100011100 8
b1000100011100 I
b1000100011100 7
b11100011100 ;
b11100011100 F
b1000000011000 !
b1000000011000 D
b1000000011000 N
b11100011100 C
b111 /
1)
#240000
0)
#250000
b1000100011100 "
b1000100011100 Q
b1001000100000 8
b1001000100000 I
b1001000100000 7
b100000100000 ;
b100000100000 F
b1000100011100 !
b1000100011100 D
b1000100011100 N
b100000100000 C
b1000 /
1)
#260000
0)
#270000
b1001000100000 "
b1001000100000 Q
b1001100100100 8
b1001100100100 I
b1001100100100 7
b100100100100 ;
b100100100100 F
b1001000100000 !
b1001000100000 D
b1001000100000 N
b100100100100 C
b1001 /
1)
#280000
0)
#290000
b1001100100100 "
b1001100100100 Q
b1010000101000 8
b1010000101000 I
b1010000101000 7
b101000101000 ;
b101000101000 F
b1001100100100 !
b1001100100100 D
b1001100100100 N
b101000101000 C
b1010 /
1)
#300000
0)
#310000
b1010000101000 "
b1010000101000 Q
b1010100101100 8
b1010100101100 I
b1010100101100 7
b101100101100 ;
b101100101100 F
b1010000101000 !
b1010000101000 D
b1010000101000 N
b101100101100 C
b1011 /
1)
#320000
0)
#330000
b1010100101100 "
b1010100101100 Q
b1011000110000 8
b1011000110000 I
b1011000110000 7
b110000110000 ;
b110000110000 F
b1010100101100 !
b1010100101100 D
b1010100101100 N
b110000110000 C
b1100 /
1)
#340000
0)
#350000
b1011000110000 "
b1011000110000 Q
b1011100110100 8
b1011100110100 I
b1011100110100 7
b110100110100 ;
b110100110100 F
b1011000110000 !
b1011000110000 D
b1011000110000 N
b110100110100 C
b1101 /
1)
#360000
0)
#370000
b1011100110100 "
b1011100110100 Q
b1100000111000 8
b1100000111000 I
b1100000111000 7
b111000111000 ;
b111000111000 F
b1011100110100 !
b1011100110100 D
b1011100110100 N
b111000111000 C
b1110 /
1)
#380000
0)
#390000
b1100000111000 "
b1100000111000 Q
b1100100111100 8
b1100100111100 I
b1100100111100 7
b111100111100 ;
b111100111100 F
b1100000111000 !
b1100000111000 D
b1100000111000 N
b111100111100 C
b1111 /
1)
#400000
0)
#410000
b1100100111100 "
b1100100111100 Q
b1101001000000 8
b1101001000000 I
b1101001000000 7
b1000001000000 ;
b1000001000000 F
b1100100111100 !
b1100100111100 D
b1100100111100 N
b1000001000000 C
b10000 /
1)
#420000
0)
#430000
b1101001000000 "
b1101001000000 Q
b1101101000100 8
b1101101000100 I
b1101101000100 7
b1000101000100 ;
b1000101000100 F
b1101001000000 !
b1101001000000 D
b1101001000000 N
b1000101000100 C
b10001 /
1)
#440000
0)
#450000
b1101101000100 "
b1101101000100 Q
b1110001001000 8
b1110001001000 I
b1110001001000 7
b1001001001000 ;
b1001001001000 F
b1101101000100 !
b1101101000100 D
b1101101000100 N
b1001001001000 C
b10010 /
1)
#460000
0)
#470000
b1110001001000 "
b1110001001000 Q
b1110101001100 8
b1110101001100 I
b1110101001100 7
b1001101001100 ;
b1001101001100 F
b1110001001000 !
b1110001001000 D
b1110001001000 N
b1001101001100 C
b10011 /
1)
#480000
0)
#490000
b1110101001100 "
b1110101001100 Q
b1111001010000 8
b1111001010000 I
b1111001010000 7
b1010001010000 ;
b1010001010000 F
b1110101001100 !
b1110101001100 D
b1110101001100 N
b1010001010000 C
b10100 /
1)
#500000
0)
#510000
b1111001010000 "
b1111001010000 Q
b1111101010100 8
b1111101010100 I
b1111101010100 7
b1010101010100 ;
b1010101010100 F
b1111001010000 !
b1111001010000 D
b1111001010000 N
b1010101010100 C
b10101 /
1)
#520000
0)
#530000
b1111101010100 "
b1111101010100 Q
b10000001011000 8
b10000001011000 I
b10000001011000 7
b1011001011000 ;
b1011001011000 F
b1111101010100 !
b1111101010100 D
b1111101010100 N
b1011001011000 C
b10110 /
1)
#540000
0)
#550000
b10000001011000 "
b10000001011000 Q
b10000101011100 8
b10000101011100 I
b10000101011100 7
b1011101011100 ;
b1011101011100 F
b10000001011000 !
b10000001011000 D
b10000001011000 N
b1011101011100 C
b10111 /
1)
#560000
0)
#570000
b10000101011100 "
b10000101011100 Q
b10001001100000 8
b10001001100000 I
b10001001100000 7
b1100001100000 ;
b1100001100000 F
b10000101011100 !
b10000101011100 D
b10000101011100 N
b1100001100000 C
b11000 /
1)
#580000
0)
#590000
b10001001100000 "
b10001001100000 Q
b10001101100100 8
b10001101100100 I
b10001101100100 7
b1100101100100 ;
b1100101100100 F
b10001001100000 !
b10001001100000 D
b10001001100000 N
b1100101100100 C
b11001 /
1)
#600000
0)
#610000
b10001101100100 "
b10001101100100 Q
b10010001101000 8
b10010001101000 I
b10010001101000 7
b1101001101000 ;
b1101001101000 F
b10001101100100 !
b10001101100100 D
b10001101100100 N
b1101001101000 C
b11010 /
1)
#620000
0)
#630000
b10010001101000 "
b10010001101000 Q
b10010101101100 8
b10010101101100 I
b10010101101100 7
b1101101101100 ;
b1101101101100 F
b10010001101000 !
b10010001101000 D
b10010001101000 N
b1101101101100 C
b11011 /
1)
#640000
0)
#650000
b10010101101100 "
b10010101101100 Q
b10011001110000 8
b10011001110000 I
b10011001110000 7
b1110001110000 ;
b1110001110000 F
b10010101101100 !
b10010101101100 D
b10010101101100 N
b1110001110000 C
b11100 /
1)
#660000
0)
#670000
b10011001110000 "
b10011001110000 Q
b10011101110100 8
b10011101110100 I
b10011101110100 7
b1110101110100 ;
b1110101110100 F
b10011001110000 !
b10011001110000 D
b10011001110000 N
b1110101110100 C
b11101 /
1)
#680000
0)
#690000
b10011101110100 "
b10011101110100 Q
b10100001111000 8
b10100001111000 I
b10100001111000 7
b1111001111000 ;
b1111001111000 F
b10011101110100 !
b10011101110100 D
b10011101110100 N
b1111001111000 C
b11110 /
1)
#700000
0)
#710000
b10100001111000 "
b10100001111000 Q
b10100101111100 8
b10100101111100 I
b10100101111100 7
b1111101111100 ;
b1111101111100 F
b10100001111000 !
b10100001111000 D
b10100001111000 N
b1111101111100 C
b11111 /
1)
#720000
0)
#730000
b10100101111100 "
b10100101111100 Q
b10101010000000 8
b10101010000000 I
b10101010000000 7
b10000010000000 ;
b10000010000000 F
b10100101111100 !
b10100101111100 D
b10100101111100 N
b10000010000000 C
b100000 /
1)
#740000
0)
#750000
b10101010000000 "
b10101010000000 Q
b10101110000100 8
b10101110000100 I
b10101110000100 7
b10000110000100 ;
b10000110000100 F
b10101010000000 !
b10101010000000 D
b10101010000000 N
b10000110000100 C
b100001 /
1)
#760000
0)
#770000
b10101110000100 "
b10101110000100 Q
b10110010001000 8
b10110010001000 I
b10110010001000 7
b10001010001000 ;
b10001010001000 F
b10101110000100 !
b10101110000100 D
b10101110000100 N
b10001010001000 C
b100010 /
1)
#780000
0)
#790000
b10110010001000 "
b10110010001000 Q
b10110110001100 8
b10110110001100 I
b10110110001100 7
b10001110001100 ;
b10001110001100 F
b10110010001000 !
b10110010001000 D
b10110010001000 N
b10001110001100 C
b100011 /
1)
#800000
0)
#810000
b10110110001100 "
b10110110001100 Q
b10111010010000 8
b10111010010000 I
b10111010010000 7
b10010010010000 ;
b10010010010000 F
b10110110001100 !
b10110110001100 D
b10110110001100 N
b10010010010000 C
b100100 /
1)
#820000
0)
#830000
b10111010010000 "
b10111010010000 Q
b10111110010100 8
b10111110010100 I
b10111110010100 7
b10010110010100 ;
b10010110010100 F
b10111010010000 !
b10111010010000 D
b10111010010000 N
b10010110010100 C
b100101 /
1)
#840000
0)
#850000
b10111110010100 "
b10111110010100 Q
b11000010011000 8
b11000010011000 I
b11000010011000 7
b10011010011000 ;
b10011010011000 F
b10111110010100 !
b10111110010100 D
b10111110010100 N
b10011010011000 C
b100110 /
1)
#860000
0)
#870000
b11000010011000 "
b11000010011000 Q
b11000110011100 8
b11000110011100 I
b11000110011100 7
b10011110011100 ;
b10011110011100 F
b11000010011000 !
b11000010011000 D
b11000010011000 N
b10011110011100 C
b100111 /
1)
#880000
0)
#890000
b11000110011100 "
b11000110011100 Q
b11001010100000 8
b11001010100000 I
b11001010100000 7
b10100010100000 ;
b10100010100000 F
b11000110011100 !
b11000110011100 D
b11000110011100 N
b10100010100000 C
b101000 /
1)
#900000
0)
#910000
b11001010100000 "
b11001010100000 Q
b11001110100100 8
b11001110100100 I
b11001110100100 7
b10100110100100 ;
b10100110100100 F
b11001010100000 !
b11001010100000 D
b11001010100000 N
b10100110100100 C
b101001 /
1)
#920000
0)
#930000
b11001110100100 "
b11001110100100 Q
b11010010101000 8
b11010010101000 I
b11010010101000 7
b10101010101000 ;
b10101010101000 F
b11001110100100 !
b11001110100100 D
b11001110100100 N
b10101010101000 C
b101010 /
1)
#940000
0)
#950000
b11010010101000 "
b11010010101000 Q
b11010110101100 8
b11010110101100 I
b11010110101100 7
b10101110101100 ;
b10101110101100 F
b11010010101000 !
b11010010101000 D
b11010010101000 N
b10101110101100 C
b101011 /
1)
#960000
0)
#970000
b11010110101100 "
b11010110101100 Q
b11011010110000 8
b11011010110000 I
b11011010110000 7
b10110010110000 ;
b10110010110000 F
b11010110101100 !
b11010110101100 D
b11010110101100 N
b10110010110000 C
b101100 /
1)
#980000
0)
#990000
b11011010110000 "
b11011010110000 Q
b11011110110100 8
b11011110110100 I
b11011110110100 7
b10110110110100 ;
b10110110110100 F
b11011010110000 !
b11011010110000 D
b11011010110000 N
b10110110110100 C
b101101 /
1)
#1000000
0)
#1010000
b11011110110100 "
b11011110110100 Q
b11100010111000 8
b11100010111000 I
b11100010111000 7
b10111010111000 ;
b10111010111000 F
b11011110110100 !
b11011110110100 D
b11011110110100 N
b10111010111000 C
b101110 /
1)
#1020000
0)
#1030000
b11100010111000 "
b11100010111000 Q
b11100110111100 8
b11100110111100 I
b11100110111100 7
b10111110111100 ;
b10111110111100 F
b11100010111000 !
b11100010111000 D
b11100010111000 N
b10111110111100 C
b101111 /
1)
#1040000
0)
#1050000
b11100110111100 "
b11100110111100 Q
b11101011000000 8
b11101011000000 I
b11101011000000 7
b11000011000000 ;
b11000011000000 F
b11100110111100 !
b11100110111100 D
b11100110111100 N
b11000011000000 C
b110000 /
1)
#1060000
0)
#1070000
b11101011000000 "
b11101011000000 Q
b11101111000100 8
b11101111000100 I
b11101111000100 7
b11000111000100 ;
b11000111000100 F
b11101011000000 !
b11101011000000 D
b11101011000000 N
b11000111000100 C
b110001 /
1)
#1080000
0)
#1090000
b11101111000100 "
b11101111000100 Q
b11110011001000 8
b11110011001000 I
b11110011001000 7
b11001011001000 ;
b11001011001000 F
b11101111000100 !
b11101111000100 D
b11101111000100 N
b11001011001000 C
b110010 /
1)
#1100000
0)
#1110000
b11110011001000 "
b11110011001000 Q
b11110111001100 8
b11110111001100 I
b11110111001100 7
b11001111001100 ;
b11001111001100 F
b11110011001000 !
b11110011001000 D
b11110011001000 N
b11001111001100 C
b110011 /
1)
#1120000
0)
#1130000
b11110111001100 "
b11110111001100 Q
b11111011010000 8
b11111011010000 I
b11111011010000 7
b11010011010000 ;
b11010011010000 F
b11110111001100 !
b11110111001100 D
b11110111001100 N
b11010011010000 C
b110100 /
1)
#1140000
0)
#1150000
b11111011010000 "
b11111011010000 Q
b11111111010100 8
b11111111010100 I
b11111111010100 7
b11010111010100 ;
b11010111010100 F
b11111011010000 !
b11111011010000 D
b11111011010000 N
b11010111010100 C
b110101 /
1)
#1160000
0)
#1170000
b11111111010100 "
b11111111010100 Q
b100000011011000 8
b100000011011000 I
b100000011011000 7
b11011011011000 ;
b11011011011000 F
b11111111010100 !
b11111111010100 D
b11111111010100 N
b11011011011000 C
b110110 /
1)
#1180000
0)
#1190000
b100000011011000 "
b100000011011000 Q
b100000111011100 8
b100000111011100 I
b100000111011100 7
b11011111011100 ;
b11011111011100 F
b100000011011000 !
b100000011011000 D
b100000011011000 N
b11011111011100 C
b110111 /
1)
#1200000
0)
#1210000
b100000111011100 "
b100000111011100 Q
b100001011100000 8
b100001011100000 I
b100001011100000 7
b11100011100000 ;
b11100011100000 F
b100000111011100 !
b100000111011100 D
b100000111011100 N
b11100011100000 C
b111000 /
1)
#1220000
0)
#1230000
b100001011100000 "
b100001011100000 Q
b100001111100100 8
b100001111100100 I
b100001111100100 7
b11100111100100 ;
b11100111100100 F
b100001011100000 !
b100001011100000 D
b100001011100000 N
b11100111100100 C
b111001 /
1)
#1240000
0)
#1250000
b100001111100100 "
b100001111100100 Q
b100010011101000 8
b100010011101000 I
b100010011101000 7
b11101011101000 ;
b11101011101000 F
b100001111100100 !
b100001111100100 D
b100001111100100 N
b11101011101000 C
b111010 /
1)
#1260000
0)
#1270000
b100010011101000 "
b100010011101000 Q
b100010111101100 8
b100010111101100 I
b100010111101100 7
b11101111101100 ;
b11101111101100 F
b100010011101000 !
b100010011101000 D
b100010011101000 N
b11101111101100 C
b111011 /
1)
#1280000
0)
