rtl/saturation_guard.v
//============================================================================
// Module:      saturation_guard
// Description: Combinational output saturation / clamping with anti-windup
//              integrator hold signal. When the raw PID output exceeds the
//              configured limits, the output is clamped and integrator_hold
//              is asserted to prevent integral windup.
//
// Fixed-Point: Signed Q8.8 — 16-bit, 1 sign + 7 integer + 8 fractional
//============================================================================

module saturation_guard #(
    parameter signed [15:0] MAX_OUT = 16'h7F00,  // +127.0 in Q8.8
    parameter signed [15:0] MIN_OUT = 16'h8100   // -127.0 in Q8.8
)(
    input  wire [15:0] raw_in,          // Raw PID output (Q8.8 signed)
    output wire [15:0] clamped_out,     // Clamped output (Q8.8 signed)
    output wire        integrator_hold  // High when output is saturated
);

    // Saturation logic (purely combinational)
    wire saturated_high = ($signed(raw_in) > $signed(MAX_OUT));
    wire saturated_low  = ($signed(raw_in) < $signed(MIN_OUT));

    assign clamped_out = saturated_high ? MAX_OUT :
                         saturated_low  ? MIN_OUT :
                         raw_in;

    // Assert integrator hold when output is at either limit
    assign integrator_hold = saturated_high | saturated_low;

endmodule

rtl/pid_controller.v
//============================================================================
// Module:      pid_controller
// Description: Parameterized PID controller using signed Q8.8 fixed-point
//              arithmetic. Implements Proportional, Integral, and Derivative
//              control with anti-windup support via integrator_hold.
//
// Fixed-Point: Signed Q8.8 — 1 sign bit, 7 integer bits, 8 fractional bits
//              Range: -128.0 to +127.99609375
//              Resolution: 1/256 ≈ 0.00390625
//============================================================================

module pid_controller #(
    parameter signed [15:0] Kp      = 16'h0100,  // 1.0  in Q8.8
    parameter signed [15:0] Ki      = 16'h001A,  // 0.1  in Q8.8 (≈26/256)
    parameter signed [15:0] Kd      = 16'h0080,  // 0.5  in Q8.8
    parameter signed [15:0] MAX_OUT = 16'h7F00,  // +127.0 in Q8.8
    parameter signed [15:0] MIN_OUT = 16'h8100   // -127.0 in Q8.8
)(
    input  wire        clk,
    input  wire        rst,
    input  wire [15:0] error_in,        // Signed Q8.8 error
    input  wire        integrator_hold,  // Freeze integrator when saturated
    output reg  [15:0] pid_out           // Signed Q8.8 PID output (raw, unclamped)
);

    // Internal registers
    reg signed [15:0] prev_error;       // Previous error for derivative term
    reg signed [31:0] integrator;       // Wider accumulator for integral term

    // Intermediate wires for combinational arithmetic
    wire signed [15:0] error_signed = $signed(error_in);

    // --- Proportional term ---
    // Q8.8 × Q8.8 = Q16.16 (32 bits). Extract [23:8] for Q8.8 result.
    wire signed [31:0] p_product = $signed(Kp) * error_signed;
    wire signed [15:0] p_term;
    assign p_term = saturate_q88(p_product);

    // --- Derivative term ---
    wire signed [15:0] error_diff = error_signed - prev_error;
    wire signed [31:0] d_product  = $signed(Kd) * error_diff;
    wire signed [15:0] d_term;
    assign d_term = saturate_q88(d_product);

    // --- Integral term (Ki × error, to be accumulated) ---
    wire signed [31:0] i_product = $signed(Ki) * error_signed;
    wire signed [15:0] i_increment;
    assign i_increment = saturate_q88(i_product);

    // --- Integrator value clamped to Q8.8 range for output ---
    wire signed [15:0] i_term;
    assign i_term = clamp_integrator(integrator);

    // --- PID sum (use wider bus to detect overflow before clamping) ---
    wire signed [31:0] pid_sum_wide = $signed(p_term) + $signed(i_term) + $signed(d_term);
    wire signed [15:0] pid_sum_clamped;
    assign pid_sum_clamped = clamp_to_range(pid_sum_wide, $signed(MAX_OUT), $signed(MIN_OUT));

    // Clocked process
    always @(posedge clk) begin
        if (rst) begin
            prev_error  <= 16'sd0;
            integrator  <= 32'sd0;
            pid_out     <= 16'sd0;
        end else begin
            // Update previous error
            prev_error <= error_signed;

            // Update integrator (with anti-windup hold)
            if (!integrator_hold) begin
                integrator <= integrator + $signed({{16{i_increment[15]}}, i_increment});
            end

            // Output the clamped PID sum
            pid_out <= pid_sum_clamped;
        end
    end

    // Function: saturate_q88
    // Extracts Q8.8 from a Q16.16 product with overflow saturation.
    function signed [15:0] saturate_q88;
        input signed [31:0] product;
        reg signed [15:0] truncated;
        reg overflow_pos, overflow_neg;
        begin
            truncated    = product[23:8];
            // Check if upper bits [31:23] are all 0 (positive) or all 1 (negative)
            // For no overflow: positive → [31:23] == 9'b0, negative → [31:23] == 9'h1FF
            overflow_pos = (product[31] == 1'b0) && (product[31:23] != 9'h000);
            overflow_neg = (product[31] == 1'b1) && (product[31:23] != 9'h1FF);

            if (overflow_pos)
                saturate_q88 = 16'h7FFF;  // Max positive Q8.8
            else if (overflow_neg)
                saturate_q88 = 16'h8000;  // Max negative Q8.8
            else
                saturate_q88 = truncated;
        end
    endfunction

    // Function: clamp_integrator
    // Clamps the 32-bit integrator accumulator to Q8.8 range.
    function signed [15:0] clamp_integrator;
        input signed [31:0] acc;
        begin
            if (acc > $signed(32'h00007FFF))
                clamp_integrator = 16'h7FFF;
            else if (acc < $signed(32'hFFFF8000))
                clamp_integrator = 16'h8000;
            else
                clamp_integrator = acc[15:0];
        end
    endfunction

    // Function: clamp_to_range
    // Clamps a wide sum to the specified [MIN, MAX] range.
    function signed [15:0] clamp_to_range;
        input signed [31:0] val;
        input signed [15:0] max_val;
        input signed [15:0] min_val;
        begin
            if (val > $signed({{16{max_val[15]}}, max_val}))
                clamp_to_range = max_val;
            else if (val < $signed({{16{min_val[15]}}, min_val}))
                clamp_to_range = min_val;
            else
                clamp_to_range = val[15:0];
        end
    endfunction

endmodule

sim/tb_pid.v
//============================================================================
// Testbench: tb_pid
// Description: Standalone Verilog testbench for pid_controller and
//              saturation_guard modules. Applies a step error input and
//              observes the PID response over 500 clock cycles.
//
// Run with Icarus Verilog:
//   iverilog -o tb_pid rtl/pid_controller.v rtl/saturation_guard.v sim/tb_pid.v
//   vvp tb_pid
//   gtkwave tb_pid.vcd  (optional waveform viewer)
//============================================================================

`timescale 1ns / 1ps

module tb_pid;

    //------------------------------------------------------------------------
    // Parameters — using moderate gains for visible response
    //------------------------------------------------------------------------
    localparam signed [15:0] Kp      = 16'h0100;  // 1.0
    localparam signed [15:0] Ki      = 16'h001A;  // ~0.1 (26/256)
    localparam signed [15:0] Kd      = 16'h0080;  // 0.5
    localparam signed [15:0] MAX_OUT = 16'h7F00;  // +127.0
    localparam signed [15:0] MIN_OUT = 16'h8100;  // -127.0

    //------------------------------------------------------------------------
    // DUT signals
    //------------------------------------------------------------------------
    reg         clk;
    reg         rst;
    reg  [15:0] error_in;

    wire [15:0] pid_raw_out;
    wire [15:0] pid_clamped_out;
    wire        integrator_hold;

    //------------------------------------------------------------------------
    // DUT instantiation: PID → Saturation Guard
    //------------------------------------------------------------------------
    pid_controller #(
        .Kp      (Kp),
        .Ki      (Ki),
        .Kd      (Kd),
        .MAX_OUT (MAX_OUT),
        .MIN_OUT (MIN_OUT)
    ) dut_pid (
        .clk             (clk),
        .rst             (rst),
        .error_in        (error_in),
        .integrator_hold (integrator_hold),
        .pid_out         (pid_raw_out)
    );

    saturation_guard #(
        .MAX_OUT (MAX_OUT),
        .MIN_OUT (MIN_OUT)
    ) dut_sat (
        .raw_in          (pid_raw_out),
        .clamped_out     (pid_clamped_out),
        .integrator_hold (integrator_hold)
    );

    //------------------------------------------------------------------------
    // Clock generation — 20 ns period (50 MHz)
    //------------------------------------------------------------------------
    initial clk = 0;
    always #10 clk = ~clk;

    //------------------------------------------------------------------------
    // Helper function: Convert Q8.8 to real for display
    //------------------------------------------------------------------------
    // Note: Icarus Verilog supports $itor for integer-to-real conversion
    function real q88_to_real;
        input [15:0] val;
        reg signed [15:0] sval;
        begin
            sval = val;
            q88_to_real = $itor(sval) / 256.0;
        end
    endfunction

    //------------------------------------------------------------------------
    // VCD dump setup
    //------------------------------------------------------------------------
    initial begin
        $dumpfile("tb_pid.vcd");
        $dumpvars(0, tb_pid);
    end

    //------------------------------------------------------------------------
    // Test sequence
    //------------------------------------------------------------------------
    integer cycle;

    initial begin
        $display("============================================================");
        $display("  PID Controller + Saturation Guard Testbench");
        $display("  Kp=%.4f  Ki=%.4f  Kd=%.4f", q88_to_real(Kp), q88_to_real(Ki), q88_to_real(Kd));
        $display("============================================================");
        $display("");
        $display("  Cycle | Error(Q8.8) | Error(dec) | PID Raw    | PID Clamp  | Hold");
        $display("  ------|-------------|------------|------------|------------|-----");

        // Initialize
        rst      = 1;
        error_in = 16'h0000;
        cycle    = 0;

        // Hold reset for 5 cycles
        repeat (5) @(posedge clk);
        rst = 0;

        // ---- TEST 1: Positive step error (+10.0 in Q8.8 = 0x0A00) ----
        $display("");
        $display("  [TEST 1] Step error: +10.0 (0x0A00)");
        error_in = 16'h0A00;  // +10.0

        repeat (100) begin
            @(posedge clk);
            cycle = cycle + 1;
            if (cycle <= 20 || cycle % 10 == 0) begin
                $display("  %5d | 0x%04h     | %8.4f   | 0x%04h     | 0x%04h     | %b",
                    cycle, error_in, q88_to_real(error_in),
                    pid_raw_out, pid_clamped_out, integrator_hold);
            end
        end

        // ---- TEST 2: Zero error (should see derivative kick, integral hold) ----
        $display("");
        $display("  [TEST 2] Step error to 0.0 (0x0000)");
        error_in = 16'h0000;

        repeat (100) begin
            @(posedge clk);
            cycle = cycle + 1;
            if (cycle <= 120 || cycle % 10 == 0) begin
                $display("  %5d | 0x%04h     | %8.4f   | 0x%04h     | 0x%04h     | %b",
                    cycle, error_in, q88_to_real(error_in),
                    pid_raw_out, pid_clamped_out, integrator_hold);
            end
        end

        // ---- TEST 3: Negative step error (-5.0 = 0xFB00) ----
        $display("");
        $display("  [TEST 3] Step error: -5.0 (0xFB00)");
        error_in = 16'hFB00;  // -5.0

        repeat (100) begin
            @(posedge clk);
            cycle = cycle + 1;
            if (cycle <= 220 || cycle % 10 == 0) begin
                $display("  %5d | 0x%04h     | %8.4f   | 0x%04h     | 0x%04h     | %b",
                    cycle, error_in, q88_to_real(error_in),
                    pid_raw_out, pid_clamped_out, integrator_hold);
            end
        end

        // ---- TEST 4: Large error to test saturation (+120.0 = 0x7800) ----
        $display("");
        $display("  [TEST 4] Large error: +120.0 (0x7800) — should saturate");
        error_in = 16'h7800;  // +120.0

        repeat (50) begin
            @(posedge clk);
            cycle = cycle + 1;
            $display("  %5d | 0x%04h     | %8.4f   | 0x%04h     | 0x%04h     | %b",
                cycle, error_in, q88_to_real(error_in),
                pid_raw_out, pid_clamped_out, integrator_hold);
        end

        // ---- TEST 5: Reset mid-operation ----
        $display("");
        $display("  [TEST 5] Assert reset — all outputs should zero");
        rst = 1;
        repeat (3) @(posedge clk);
        cycle = cycle + 3;
        $display("  %5d | 0x%04h     | %8.4f   | 0x%04h     | 0x%04h     | %b",
            cycle, error_in, q88_to_real(error_in),
            pid_raw_out, pid_clamped_out, integrator_hold);

        // Verify reset behavior
        if (pid_raw_out == 16'h0000 && pid_clamped_out == 16'h0000)
            $display("  [PASS] Reset cleared PID output correctly.");
        else
            $display("  [FAIL] PID output not zero after reset! raw=0x%04h clamp=0x%04h",
                pid_raw_out, pid_clamped_out);

        rst = 0;

        // ---- Summary ----
        $display("");
        $display("============================================================");
        $display("  Testbench complete. Review tb_pid.vcd for waveforms.");
        $display("============================================================");
        $finish;
    end

endmodule

tb_pid.vcd
$date
	Sat May 09 20:47:25 2026
$end
$version
	Icarus Verilog
$end
$timescale
	1ps
$end
$scope module tb_pid $end
$var wire 16 ! pid_raw_out [15:0] $end
$var wire 16 " pid_clamped_out [15:0] $end
$var wire 1 # integrator_hold $end
$var parameter 16 $ Kd $end
$var parameter 16 % Ki $end
$var parameter 16 & Kp $end
$var parameter 16 ' MAX_OUT $end
$var parameter 16 ( MIN_OUT $end
$var reg 1 ) clk $end
$var reg 16 * error_in [15:0] $end
$var reg 1 + rst $end
$var integer 32 , cycle [31:0] $end
$scope function q88_to_real $end
$var reg 16 - sval [15:0] $end
$var reg 16 . val [15:0] $end
$upscope $end
$scope module dut_pid $end
$var wire 1 ) clk $end
$var wire 16 / error_in [15:0] $end
$var wire 16 0 error_signed [15:0] $end
$var wire 1 + rst $end
$var wire 32 1 pid_sum_wide [31:0] $end
$var wire 16 2 pid_sum_clamped [15:0] $end
$var wire 16 3 p_term [15:0] $end
$var wire 32 4 p_product [31:0] $end
$var wire 1 # integrator_hold $end
$var wire 16 5 i_term [15:0] $end
$var wire 32 6 i_product [31:0] $end
$var wire 16 7 i_increment [15:0] $end
$var wire 16 8 error_diff [15:0] $end
$var wire 16 9 d_term [15:0] $end
$var wire 32 : d_product [31:0] $end
$var parameter 16 ; Kd $end
$var parameter 16 < Ki $end
$var parameter 16 = Kp $end
$var parameter 16 > MAX_OUT $end
$var parameter 16 ? MIN_OUT $end
$var reg 32 @ integrator [31:0] $end
$var reg 16 A pid_out [15:0] $end
$var reg 16 B prev_error [15:0] $end
$scope function clamp_integrator $end
$var reg 32 C acc [31:0] $end
$upscope $end
$scope function clamp_to_range $end
$var reg 16 D max_val [15:0] $end
$var reg 16 E min_val [15:0] $end
$var reg 32 F val [31:0] $end
$upscope $end
$scope function saturate_q88 $end
$var reg 1 G overflow_neg $end
$var reg 1 H overflow_pos $end
$var reg 32 I product [31:0] $end
$var reg 16 J truncated [15:0] $end
$upscope $end
$upscope $end
$scope module dut_sat $end
$var wire 1 # integrator_hold $end
$var wire 16 K raw_in [15:0] $end
$var wire 1 L saturated_low $end
$var wire 1 M saturated_high $end
$var wire 16 N clamped_out [15:0] $end
$var parameter 16 O MAX_OUT $end
$var parameter 16 P MIN_OUT $end
$upscope $end
$upscope $end
$enddefinitions $end
$comment Show the parameter values. $end
$dumpall
b1000000100000000 P
b111111100000000 O
b1000000100000000 ?
b111111100000000 >
b100000000 =
b11010 <
b10000000 ;
b1000000100000000 (
b111111100000000 '
b100000000 &
b11010 %
b10000000 $
$end
#0
$dumpvars
bx N
xM
xL
bx K
b0 J
b0 I
0H
0G
bx F
b1000000100000000 E
b111111100000000 D
bx C
bx B
bx A
bx @
bx :
bx 9
bx 8
b0 7
b0 6
bx 5
b0 4
b0 3
bx 2
bx 1
b0 0
b0 /
b10000000 .
b10000000 -
b0 ,
1+
b0 *
0)
x#
bx "
bx !
$end
#10000
b0 2
b0 F
b0 "
b0 N
0#
b0 1
b0 5
b0 C
b0 9
0M
0L
b0 !
b0 A
b0 K
b0 @
b0 :
b0 8
b0 B
1)
#20000
0)
#30000
1)
#40000
0)
#50000
1)
#60000
0)
#70000
1)
#80000
0)
#90000
b101000000000 B
b101000000000 2
b101000000000 F
b101000000000 3
b101000000000 1
b0 9
b100000100 7
b0 J
b0 I
b10100000000000000000 4
b0 :
b0 8
b10000010000000000 6
b101000000000 *
b101000000000 /
b101000000000 0
0+
1)
#100000
0)
#110000
b101000000000 "
b101000000000 N
b101100000100 2
b101100000100 F
b101100000100 1
b100000100 5
b100000100 C
b101000000000 !
b101000000000 A
b101000000000 K
b100000100 @
b101000000000 -
b101000000000 .
b1 ,
1)
#120000
0)
#130000
b101100000100 "
b101100000100 N
b110000001000 2
b110000001000 F
b110000001000 1
b1000001000 5
b1000001000 C
b101100000100 !
b101100000100 A
b101100000100 K
b1000001000 @
b10 ,
1)
#140000
0)
#150000
b110000001000 "
b110000001000 N
b110100001100 2
b110100001100 F
b110100001100 1
b1100001100 5
b1100001100 C
b110000001000 !
b110000001000 A
b110000001000 K
b1100001100 @
b11 ,
1)
#160000
0)
#170000
b110100001100 "
b110100001100 N
b111000010000 2
b111000010000 F
b111000010000 1
b10000010000 5
b10000010000 C
b110100001100 !
b110100001100 A
b110100001100 K
b10000010000 @
b100 ,
1)
#180000
0)
#190000
b111000010000 "
b111000010000 N
b111100010100 2
b111100010100 F
b111100010100 1
b10100010100 5
b10100010100 C
b111000010000 !
b111000010000 A
b111000010000 K
b10100010100 @
b101 ,
1)
#200000
0)
#210000
b111100010100 "
b111100010100 N
b1000000011000 2
b1000000011000 F
b1000000011000 1
b11000011000 5
b11000011000 C
b111100010100 !
b111100010100 A
b111100010100 K
b11000011000 @
b110 ,
1)
#220000
0)
#230000
b1000000011000 "
b1000000011000 N
b1000100011100 2
b1000100011100 F
b1000100011100 1
b11100011100 5
b11100011100 C
b1000000011000 !
b1000000011000 A
b1000000011000 K
b11100011100 @
b111 ,
1)
#240000
0)
#250000
b1000100011100 "
b1000100011100 N
b1001000100000 2
b1001000100000 F
b1001000100000 1
b100000100000 5
b100000100000 C
b1000100011100 !
b1000100011100 A
b1000100011100 K
b100000100000 @
b1000 ,
1)
#260000
0)
#270000
b1001000100000 "
b1001000100000 N
b1001100100100 2
b1001100100100 F
b1001100100100 1
b100100100100 5
b100100100100 C
b1001000100000 !
b1001000100000 A
b1001000100000 K
b100100100100 @
b1001 ,
1)
#280000
0)
#290000
b1001100100100 "
b1001100100100 N
b1010000101000 2
b1010000101000 F
b1010000101000 1
b101000101000 5
b101000101000 C
b1001100100100 !
b1001100100100 A
b1001100100100 K
b101000101000 @
b1010 ,
1)
#300000
0)
#310000
b1010000101000 "
b1010000101000 N
b1010100101100 2
b1010100101100 F
b1010100101100 1
b101100101100 5
b101100101100 C
b1010000101000 !
b1010000101000 A
b1010000101000 K
b101100101100 @
b1011 ,
1)
#320000
0)
#330000
b1010100101100 "
b1010100101100 N
b1011000110000 2
b1011000110000 F
b1011000110000 1
b110000110000 5
b110000110000 C
b1010100101100 !
b1010100101100 A
b1010100101100 K
b110000110000 @
b1100 ,
1)
#340000
0)
#350000
b1011000110000 "
b1011000110000 N
b1011100110100 2
b1011100110100 F
b1011100110100 1
b110100110100 5
b110100110100 C
b1011000110000 !
b1011000110000 A
b1011000110000 K
b110100110100 @
b1101 ,
1)
#360000
0)
#370000
b1011100110100 "
b1011100110100 N
b1100000111000 2
b1100000111000 F
b1100000111000 1
b111000111000 5
b111000111000 C
b1011100110100 !
b1011100110100 A
b1011100110100 K
b111000111000 @
b1110 ,
1)
#380000
0)
#390000
b1100000111000 "
b1100000111000 N
b1100100111100 2
b1100100111100 F
b1100100111100 1
b111100111100 5
b111100111100 C
b1100000111000 !
b1100000111000 A
b1100000111000 K
b111100111100 @
b1111 ,
1)
#400000
0)
#410000
b1100100111100 "
b1100100111100 N
b1101001000000 2
b1101001000000 F
b1101001000000 1
b1000001000000 5
b1000001000000 C
b1100100111100 !
b1100100111100 A
b1100100111100 K
b1000001000000 @
b10000 ,
1)
#420000
0)
#430000
b1101001000000 "
b1101001000000 N
b1101101000100 2
b1101101000100 F
b1101101000100 1
b1000101000100 5
b1000101000100 C
b1101001000000 !
b1101001000000 A
b1101001000000 K
b1000101000100 @
b10001 ,
1)
#440000
0)
#450000
b1101101000100 "
b1101101000100 N
b1110001001000 2
b1110001001000 F
b1110001001000 1
b1001001001000 5
b1001001001000 C
b1101101000100 !
b1101101000100 A
b1101101000100 K
b1001001001000 @
b10010 ,
1)
#460000
0)
#470000
b1110001001000 "
b1110001001000 N
b1110101001100 2
b1110101001100 F
b1110101001100 1
b1001101001100 5
b1001101001100 C
b1110001001000 !
b1110001001000 A
b1110001001000 K
b1001101001100 @
b10011 ,
1)
#480000
0)
#490000
b1110101001100 "
b1110101001100 N
b1111001010000 2
b1111001010000 F
b1111001010000 1
b1010001010000 5
b1010001010000 C
b1110101001100 !
b1110101001100 A
b1110101001100 K
b1010001010000 @
b10100 ,
1)
#500000
0)
#510000
b1111001010000 "
b1111001010000 N
b1111101010100 2
b1111101010100 F
b1111101010100 1
b1010101010100 5
b1010101010100 C
b1111001010000 !
b1111001010000 A
b1111001010000 K
b1010101010100 @
b10101 ,
1)
#520000
0)
#530000
b1111101010100 "
b1111101010100 N
b10000001011000 2
b10000001011000 F
b10000001011000 1
b1011001011000 5
b1011001011000 C
b1111101010100 !
b1111101010100 A
b1111101010100 K
b1011001011000 @
b10110 ,
1)
#540000
0)
#550000
b10000001011000 "
b10000001011000 N
b10000101011100 2
b10000101011100 F
b10000101011100 1
b1011101011100 5
b1011101011100 C
b10000001011000 !
b10000001011000 A
b10000001011000 K
b1011101011100 @
b10111 ,
1)
#560000
0)
#570000
b10000101011100 "
b10000101011100 N
b10001001100000 2
b10001001100000 F
b10001001100000 1
b1100001100000 5
b1100001100000 C
b10000101011100 !
b10000101011100 A
b10000101011100 K
b1100001100000 @
b11000 ,
1)
#580000
0)
#590000
b10001001100000 "
b10001001100000 N
b10001101100100 2
b10001101100100 F
b10001101100100 1
b1100101100100 5
b1100101100100 C
b10001001100000 !
b10001001100000 A
b10001001100000 K
b1100101100100 @
b11001 ,
1)
#600000
0)
#610000
b10001101100100 "
b10001101100100 N
b10010001101000 2
b10010001101000 F
b10010001101000 1
b1101001101000 5
b1101001101000 C
b10001101100100 !
b10001101100100 A
b10001101100100 K
b1101001101000 @
b11010 ,
1)
#620000
0)
#630000
b10010001101000 "
b10010001101000 N
b10010101101100 2
b10010101101100 F
b10010101101100 1
b1101101101100 5
b1101101101100 C
b10010001101000 !
b10010001101000 A
b10010001101000 K
b1101101101100 @
b11011 ,
1)
#640000
0)
#650000
b10010101101100 "
b10010101101100 N
b10011001110000 2
b10011001110000 F
b10011001110000 1
b1110001110000 5
b1110001110000 C
b10010101101100 !
b10010101101100 A
b10010101101100 K
b1110001110000 @
b11100 ,
1)
#660000
0)
#670000
b10011001110000 "
b10011001110000 N
b10011101110100 2
b10011101110100 F
b10011101110100 1
b1110101110100 5
b1110101110100 C
b10011001110000 !
b10011001110000 A
b10011001110000 K
b1110101110100 @
b11101 ,
1)
#680000
0)
#690000
b10011101110100 "
b10011101110100 N
b10100001111000 2
b10100001111000 F
b10100001111000 1
b1111001111000 5
b1111001111000 C
b10011101110100 !
b10011101110100 A
b10011101110100 K
b1111001111000 @
b11110 ,
1)
#700000
0)
#710000
b10100001111000 "
b10100001111000 N
b10100101111100 2
b10100101111100 F
b10100101111100 1
b1111101111100 5
b1111101111100 C
b10100001111000 !
b10100001111000 A
b10100001111000 K
b1111101111100 @
b11111 ,
1)
#720000
0)
#730000
b10100101111100 "
b10100101111100 N
b10101010000000 2
b10101010000000 F
b10101010000000 1
b10000010000000 5
b10000010000000 C
b10100101111100 !
b10100101111100 A
b10100101111100 K
b10000010000000 @
b100000 ,
1)
#740000
0)
#750000
b10101010000000 "
b10101010000000 N
b10101110000100 2
b10101110000100 F
b10101110000100 1
b10000110000100 5
b10000110000100 C
b10101010000000 !
b10101010000000 A
b10101010000000 K
b10000110000100 @
b100001 ,
1)
#760000
0)
#770000
b10101110000100 "
b10101110000100 N
b10110010001000 2
b10110010001000 F
b10110010001000 1
b10001010001000 5
b10001010001000 C
b10101110000100 !
b10101110000100 A
b10101110000100 K
b10001010001000 @
b100010 ,
1)
#780000
0)
#790000
b10110010001000 "
b10110010001000 N
b10110110001100 2
b10110110001100 F
b10110110001100 1
b10001110001100 5
b10001110001100 C
b10110010001000 !
b10110010001000 A
b10110010001000 K
b10001110001100 @
b100011 ,
1)
#800000
0)
#810000
b10110110001100 "
b10110110001100 N
b10111010010000 2
b10111010010000 F
b10111010010000 1
b10010010010000 5
b10010010010000 C
b10110110001100 !
b10110110001100 A
b10110110001100 K
b10010010010000 @
b100100 ,
1)
#820000
0)
#830000
b10111010010000 "
b10111010010000 N
b10111110010100 2
b10111110010100 F
b10111110010100 1
b10010110010100 5
b10010110010100 C
b10111010010000 !
b10111010010000 A
b10111010010000 K
b10010110010100 @
b100101 ,
1)
#840000
0)
#850000
b10111110010100 "
b10111110010100 N
b11000010011000 2
b11000010011000 F
b11000010011000 1
b10011010011000 5
b10011010011000 C
b10111110010100 !
b10111110010100 A
b10111110010100 K
b10011010011000 @
b100110 ,
1)
#860000
0)
#870000
b11000010011000 "
b11000010011000 N
b11000110011100 2
b11000110011100 F
b11000110011100 1
b10011110011100 5
b10011110011100 C
b11000010011000 !
b11000010011000 A
b11000010011000 K
b10011110011100 @
b100111 ,
1)
#880000
0)
#890000
b11000110011100 "
b11000110011100 N
b11001010100000 2
b11001010100000 F
b11001010100000 1
b10100010100000 5
b10100010100000 C
b11000110011100 !
b11000110011100 A
b11000110011100 K
b10100010100000 @
b101000 ,
1)
#900000
0)
#910000
b11001010100000 "
b11001010100000 N
b11001110100100 2
b11001110100100 F
b11001110100100 1
b10100110100100 5
b10100110100100 C
b11001010100000 !
b11001010100000 A
b11001010100000 K
b10100110100100 @
b101001 ,
1)
#920000
0)
#930000
b11001110100100 "
b11001110100100 N
b11010010101000 2
b11010010101000 F
b11010010101000 1
b10101010101000 5
b10101010101000 C
b11001110100100 !
b11001110100100 A
b11001110100100 K
b10101010101000 @
b101010 ,
1)
#940000
0)
#950000
b11010010101000 "
b11010010101000 N
b11010110101100 2
b11010110101100 F
b11010110101100 1
b10101110101100 5
b10101110101100 C
b11010010101000 !
b11010010101000 A
b11010010101000 K
b10101110101100 @
b101011 ,
1)
#960000
0)
#970000
b11010110101100 "
b11010110101100 N
b11011010110000 2
b11011010110000 F
b11011010110000 1
b10110010110000 5
b10110010110000 C
b11010110101100 !
b11010110101100 A
b11010110101100 K
b10110010110000 @
b101100 ,
1)
#980000
0)
#990000
b11011010110000 "
b11011010110000 N
b11011110110100 2
b11011110110100 F
b11011110110100 1
b10110110110100 5
b10110110110100 C
b11011010110000 !
b11011010110000 A
b11011010110000 K
b10110110110100 @
b101101 ,
1)
#1000000
0)
#1010000
b11011110110100 "
b11011110110100 N
b11100010111000 2
b11100010111000 F
b11100010111000 1
b10111010111000 5
b10111010111000 C
b11011110110100 !
b11011110110100 A
b11011110110100 K
b10111010111000 @
b101110 ,
1)
#1020000
0)
#1030000
b11100010111000 "
b11100010111000 N
b11100110111100 2
b11100110111100 F
b11100110111100 1
b10111110111100 5
b10111110111100 C
b11100010111000 !
b11100010111000 A
b11100010111000 K
b10111110111100 @
b101111 ,
1)
#1040000
0)
#1050000
b11100110111100 "
b11100110111100 N
b11101011000000 2
b11101011000000 F
b11101011000000 1
b11000011000000 5
b11000011000000 C
b11100110111100 !
b11100110111100 A
b11100110111100 K
b11000011000000 @
b110000 ,
1)
#1060000
0)
#1070000
b11101011000000 "
b11101011000000 N
b11101111000100 2
b11101111000100 F
b11101111000100 1
b11000111000100 5
b11000111000100 C
b11101011000000 !
b11101011000000 A
b11101011000000 K
b11000111000100 @
b110001 ,
1)
#1080000
0)
#1090000
b11101111000100 "
b11101111000100 N
b11110011001000 2
b11110011001000 F
b11110011001000 1
b11001011001000 5
b11001011001000 C
b11101111000100 !
b11101111000100 A
b11101111000100 K
b11001011001000 @
b110010 ,
1)
#1100000
0)
#1110000
b11110011001000 "
b11110011001000 N
b11110111001100 2
b11110111001100 F
b11110111001100 1
b11001111001100 5
b11001111001100 C
b11110011001000 !
b11110011001000 A
b11110011001000 K
b11001111001100 @
b110011 ,
1)
#1120000
0)
#1130000
b11110111001100 "
b11110111001100 N
b11111011010000 2
b11111011010000 F
b11111011010000 1
b11010011010000 5
b11010011010000 C
b11110111001100 !
b11110111001100 A
b11110111001100 K
b11010011010000 @
b110100 ,
1)
#1140000
0)
#1150000
b11111011010000 "
b11111011010000 N
b11111111010100 2
b11111111010100 F
b11111111010100 1
b11010111010100 5
b11010111010100 C
b11111011010000 !
b11111011010000 A
b11111011010000 K
b11010111010100 @
b110101 ,
1)
#1160000
0)
#1170000
b11111111010100 "
b11111111010100 N
b100000011011000 2
b100000011011000 F
b100000011011000 1
b11011011011000 5
b11011011011000 C
b11111111010100 !
b11111111010100 A
b11111111010100 K
b11011011011000 @
b110110 ,
1)
#1180000
0)
#1190000
b100000011011000 "
b100000011011000 N
b100000111011100 2
b100000111011100 F
b100000111011100 1
b11011111011100 5
b11011111011100 C
b100000011011000 !
b100000011011000 A
b100000011011000 K
b11011111011100 @
b110111 ,
1)
#1200000
0)
#1210000
b100000111011100 "
b100000111011100 N
b100001011100000 2
b100001011100000 F
b100001011100000 1
b11100011100000 5
b11100011100000 C
b100000111011100 !
b100000111011100 A
b100000111011100 K
b11100011100000 @
b111000 ,
1)
#1220000
0)
#1230000
b100001011100000 "
b100001011100000 N
b100001111100100 2
b100001111100100 F
b100001111100100 1
b11100111100100 5
b11100111100100 C
b100001011100000 !
b100001011100000 A
b100001011100000 K
b11100111100100 @
b111001 ,
1)
#1240000
0)
#1250000
b100001111100100 "
b100001111100100 N
b100010011101000 2
b100010011101000 F
b100010011101000 1
b11101011101000 5
b11101011101000 C
b100001111100100 !
b100001111100100 A
b100001111100100 K
b11101011101000 @
b111010 ,
1)
#1260000
0)
#1270000
b100010011101000 "
b100010011101000 N
b100010111101100 2
b100010111101100 F
b100010111101100 1
b11101111101100 5
b11101111101100 C
b100010011101000 !
b100010011101000 A
b100010011101000 K
b11101111101100 @
b111011 ,
1)
#1280000
0)
#1290000
b100010111101100 "
b100010111101100 N
b100011011110000 2
b100011011110000 F
b100011011110000 1
b11110011110000 5
b11110011110000 C
b100010111101100 !
b100010111101100 A
b100010111101100 K
b11110011110000 @
b111100 ,
1)
#1300000
0)
#1310000
b100011011110000 "
b100011011110000 N
b100011111110100 2
b100011111110100 F
b100011111110100 1
b11110111110100 5
b11110111110100 C
b100011011110000 !
b100011011110000 A
b100011011110000 K
b11110111110100 @
b111101 ,
1)
#1320000
0)
#1330000
b100011111110100 "
b100011111110100 N
b100100011111000 2
b100100011111000 F
b100100011111000 1
b11111011111000 5
b11111011111000 C
b100011111110100 !
b100011111110100 A
b100011111110100 K
b11111011111000 @
b111110 ,
1)
#1340000
0)
#1350000
b100100011111000 "
b100100011111000 N
b100100111111100 2
b100100111111100 F
b100100111111100 1
b11111111111100 5
b11111111111100 C
b100100011111000 !
b100100011111000 A
b100100011111000 K
b11111111111100 @
b111111 ,
1)
#1360000
0)
#1370000
b100100111111100 "
b100100111111100 N
b100101100000000 2
b100101100000000 F
b100101100000000 1
b100000100000000 5
b100000100000000 C
b100100111111100 !
b100100111111100 A
b100100111111100 K
b100000100000000 @
b1000000 ,
1)
#1380000
0)
