rtl/saturation_guard.v
//============================================================================
// Module:      saturation_guard
// Description: Combinational output saturation / clamping with anti-windup
//              integrator hold signal. When the raw PID output exceeds the
//              configured limits, the output is clamped and integrator_hold
//              is asserted to prevent integral windup.
//
// Fixed-Point: Signed Q8.8 — 16-bit, 1 sign + 7 integer + 8 fractional
//============================================================================

module saturation_guard #(
    parameter signed [15:0] MAX_OUT = 16'h7F00,  // +127.0 in Q8.8
    parameter signed [15:0] MIN_OUT = 16'h8100   // -127.0 in Q8.8
)(
    input  wire [15:0] raw_in,          // Raw PID output (Q8.8 signed)
    output wire [15:0] clamped_out,     // Clamped output (Q8.8 signed)
    output wire        integrator_hold, // High when output is saturated
    output wire        overflow         // High when output is saturated
);

    // Saturation logic (purely combinational)
    wire saturated_high = ($signed(raw_in) > $signed(MAX_OUT));
    wire saturated_low  = ($signed(raw_in) < $signed(MIN_OUT));

    assign clamped_out = saturated_high ? MAX_OUT :
                         saturated_low  ? MIN_OUT :
                         raw_in;

    // Assert integrator hold when output is at either limit
    assign integrator_hold = saturated_high | saturated_low;
    assign overflow = saturated_high | saturated_low;

endmodule

rtl/pid_controller.v
//============================================================================
// Module:      pid_controller
// Description: Parameterized PID controller using signed Q8.8 fixed-point
//              arithmetic. Implements Proportional, Integral, and Derivative
//              control with anti-windup support via integrator_hold.
//
// Fixed-Point: Signed Q8.8 — 1 sign bit, 7 integer bits, 8 fractional bits
//              Range: -128.0 to +127.99609375
//              Resolution: 1/256 ≈ 0.00390625
//============================================================================

module pid_controller #(
    parameter signed [15:0] MAX_OUT = 16'h7F00,  // +127.0 in Q8.8
    parameter signed [15:0] MIN_OUT = 16'h8100   // -127.0 in Q8.8
)(
    input  wire        clk,
    input  wire        rst,
    // Runtime-configurable PID gains (Q8.8 signed)
    input  wire [15:0] Kp,               // Proportional gain
    input  wire [15:0] Ki,               // Integral gain
    input  wire [15:0] Kd,               // Derivative gain
    input  wire [15:0] error_in,         // Signed Q8.8 error
    input  wire        integrator_hold,  // Freeze integrator when saturated
    output reg  [15:0] pid_out,          // Signed Q8.8 PID output (raw, unclamped)
    output reg         overflow          // High when internal arithmetic overflows
);

    // Internal registers
    reg signed [15:0] prev_error;       // Previous error for derivative term
    reg signed [31:0] integrator;       // Wider accumulator for integral term

    // Intermediate wires for combinational arithmetic
    wire signed [15:0] error_signed = $signed(error_in);

    // --- Proportional term ---
    // Q8.8 × Q8.8 = Q16.16 (32 bits). Extract [23:8] for Q8.8 result.
    wire signed [31:0] p_product = $signed(Kp) * error_signed;
    wire signed [15:0] p_term;
    assign p_term = saturate_q88(p_product);

    // --- Derivative term ---
    // Compute difference using 17 bits to avoid silent 16-bit wraparound
    wire signed [16:0] error_diff_wide = $signed(error_signed) - $signed(prev_error);
    wire signed [15:0] error_diff = clamp_diff(error_diff_wide);
    wire signed [31:0] d_product  = $signed(Kd) * error_diff;
    wire signed [15:0] d_term;
    assign d_term = saturate_q88(d_product);

    // --- Integral term (Ki × error, to be accumulated) ---
    wire signed [31:0] i_product = $signed(Ki) * error_signed;
    wire signed [15:0] i_increment;
    assign i_increment = saturate_q88(i_product);

    // --- Integrator value clamped to Q8.8 range for output ---
    wire signed [15:0] i_term;
    assign i_term = clamp_integrator(integrator);

    // --- PID sum (use wider bus to detect overflow before clamping) ---
    wire signed [31:0] pid_sum_wide = $signed(p_term) + $signed(i_term) + $signed(d_term);
    wire signed [15:0] pid_sum_clamped;
    assign pid_sum_clamped = clamp_to_range(pid_sum_wide, $signed(MAX_OUT), $signed(MIN_OUT));

    // --- Overflow detection logic ---
    wire p_overflow = (p_product[31] == 1'b0 && p_product[31:23] != 9'h000) ||
                      (p_product[31] == 1'b1 && p_product[31:23] != 9'h1FF);
    wire i_overflow = (i_product[31] == 1'b0 && i_product[31:23] != 9'h000) ||
                      (i_product[31] == 1'b1 && i_product[31:23] != 9'h1FF);
    wire d_overflow = (d_product[31] == 1'b0 && d_product[31:23] != 9'h000) ||
                      (d_product[31] == 1'b1 && d_product[31:23] != 9'h1FF);
    wire diff_overflow = (error_diff_wide > 17'sd32767) || (error_diff_wide < -17'sd32768);
    wire sum_overflow = (pid_sum_wide > $signed({{16{MAX_OUT[15]}}, MAX_OUT})) ||
                        (pid_sum_wide < $signed({{16{MIN_OUT[15]}}, MIN_OUT}));
    
    wire any_overflow = p_overflow | i_overflow | d_overflow | diff_overflow | sum_overflow;

    // Clocked process
    always @(posedge clk) begin
        if (rst) begin
            prev_error  <= 16'sd0;
            integrator  <= 32'sd0;
            pid_out     <= 16'sd0;
            overflow    <= 1'b0;
        end else begin
            // Update previous error
            prev_error <= error_signed;

            // Update integrator (with anti-windup hold)
            if (!integrator_hold) begin
                integrator <= integrator + $signed({{16{i_increment[15]}}, i_increment});
            end

            // Output the clamped PID sum
            pid_out <= pid_sum_clamped;
            
            // Update overflow flag
            overflow <= any_overflow;
        end
    end

    // Function: saturate_q88
    // Extracts Q8.8 from a Q16.16 product with overflow saturation.
    function signed [15:0] saturate_q88;
        input signed [31:0] product;
        reg signed [15:0] truncated;
        reg overflow_pos, overflow_neg;
        begin
            truncated    = product[23:8];
            // Check if upper bits [31:23] are all 0 (positive) or all 1 (negative)
            // For no overflow: positive → [31:23] == 9'b0, negative → [31:23] == 9'h1FF
            overflow_pos = (product[31] == 1'b0) && (product[31:23] != 9'h000);
            overflow_neg = (product[31] == 1'b1) && (product[31:23] != 9'h1FF);

            if (overflow_pos)
                saturate_q88 = 16'h7FFF;  // Max positive Q8.8
            else if (overflow_neg)
                saturate_q88 = 16'h8000;  // Max negative Q8.8
            else
                saturate_q88 = truncated;
        end
    endfunction

    // Function: clamp_integrator
    // Clamps the 32-bit integrator accumulator to Q8.8 range.
    function signed [15:0] clamp_integrator;
        input signed [31:0] acc;
        begin
            if (acc > $signed(32'h00007FFF))
                clamp_integrator = 16'h7FFF;
            else if (acc < $signed(32'hFFFF8000))
                clamp_integrator = 16'h8000;
            else
                clamp_integrator = acc[15:0];
        end
    endfunction

    // Function: clamp_to_range
    // Clamps a wide sum to the specified [MIN, MAX] range.
    function signed [15:0] clamp_to_range;
        input signed [31:0] val;
        input signed [15:0] max_val;
        input signed [15:0] min_val;
        begin
            if (val > $signed({{16{max_val[15]}}, max_val}))
                clamp_to_range = max_val;
            else if (val < $signed({{16{min_val[15]}}, min_val}))
                clamp_to_range = min_val;
            else
                clamp_to_range = val[15:0];
        end
    endfunction

    // Function: clamp_diff
    // Clamps a 17-bit difference to 16-bit Q8.8 range.
    function signed [15:0] clamp_diff;
        input signed [16:0] diff;
        begin
            if (diff > 17'sd32767)
                clamp_diff = 16'h7FFF;
            else if (diff < -17'sd32768)
                clamp_diff = 16'h8000;
            else
                clamp_diff = diff[15:0];
        end
    endfunction

endmodule

sim/tb_pid.v
//============================================================================
// Testbench: tb_pid
// Description: Standalone Verilog testbench for pid_controller and
//              saturation_guard modules. Applies a step error input and
//              observes the PID response over 500 clock cycles.
//
//              Updated for runtime gain inputs: Kp/Ki/Kd are now driven
//              as reg signals rather than compile-time parameters.
//
// Run with Icarus Verilog:
//   iverilog -o tb_pid rtl/pid_controller.v rtl/saturation_guard.v sim/tb_pid.v
//   vvp tb_pid
//   gtkwave tb_pid.vcd  (optional waveform viewer)
//============================================================================

`timescale 1ns / 1ps

module tb_pid;

    //------------------------------------------------------------------------
    // Gain values — driven as runtime signals
    //------------------------------------------------------------------------
    localparam signed [15:0] KP_VAL  = 16'h0100;  // 1.0
    localparam signed [15:0] KI_VAL  = 16'h001A;  // ~0.1 (26/256)
    localparam signed [15:0] KD_VAL  = 16'h0080;  // 0.5
    localparam signed [15:0] MAX_OUT = 16'h7F00;  // +127.0
    localparam signed [15:0] MIN_OUT = 16'h8100;  // -127.0

    //------------------------------------------------------------------------
    // DUT signals
    //------------------------------------------------------------------------
    reg         clk;
    reg         rst;
    reg  [15:0] error_in;
    reg  [15:0] kp_reg;
    reg  [15:0] ki_reg;
    reg  [15:0] kd_reg;

    wire [15:0] pid_raw_out;
    wire [15:0] pid_clamped_out;
    wire        integrator_hold;
    wire        pid_overflow;
    wire        sat_overflow;

    //------------------------------------------------------------------------
    // DUT instantiation: PID → Saturation Guard
    //------------------------------------------------------------------------
    pid_controller #(
        .MAX_OUT (MAX_OUT),
        .MIN_OUT (MIN_OUT)
    ) dut_pid (
        .clk             (clk),
        .rst             (rst),
        .Kp              (kp_reg),
        .Ki              (ki_reg),
        .Kd              (kd_reg),
        .error_in        (error_in),
        .integrator_hold (integrator_hold),
        .pid_out         (pid_raw_out),
        .overflow        (pid_overflow)
    );

    saturation_guard #(
        .MAX_OUT (MAX_OUT),
        .MIN_OUT (MIN_OUT)
    ) dut_sat (
        .raw_in          (pid_raw_out),
        .clamped_out     (pid_clamped_out),
        .integrator_hold (integrator_hold),
        .overflow        (sat_overflow)
    );

    //------------------------------------------------------------------------
    // Clock generation — 20 ns period (50 MHz)
    //------------------------------------------------------------------------
    initial clk = 0;
    always #10 clk = ~clk;

    //------------------------------------------------------------------------
    // Helper function: Convert Q8.8 to real for display
    //------------------------------------------------------------------------
    // Note: Icarus Verilog supports $itor for integer-to-real conversion
    function real q88_to_real;
        input [15:0] val;
        reg signed [15:0] sval;
        begin
            sval = val;
            q88_to_real = $itor(sval) / 256.0;
        end
    endfunction

    //------------------------------------------------------------------------
    // VCD dump setup
    //------------------------------------------------------------------------
    initial begin
        $dumpfile("tb_pid.vcd");
        $dumpvars(0, tb_pid);
    end

    //------------------------------------------------------------------------
    // Test sequence
    //------------------------------------------------------------------------
    integer cycle;

    initial begin
        $display("============================================================");
        $display("  PID Controller + Saturation Guard Testbench");
        $display("  Kp=%.4f  Ki=%.4f  Kd=%.4f", q88_to_real(KP_VAL), q88_to_real(KI_VAL), q88_to_real(KD_VAL));
        $display("============================================================");
        $display("");
        $display("  Cycle | Error(Q8.8) | Error(dec) | PID Raw    | PID Clamp  | Hold | Ovf");
        $display("  ------|-------------|------------|------------|------------|------|-----");

        // Initialize
        rst      = 1;
        error_in = 16'h0000;
        kp_reg   = KP_VAL;
        ki_reg   = KI_VAL;
        kd_reg   = KD_VAL;
        cycle    = 0;

        // Hold reset for 5 cycles
        repeat (5) @(posedge clk);
        rst = 0;

        // ---- TEST 1: Positive step error (+10.0 in Q8.8 = 0x0A00) ----
        $display("");
        $display("  [TEST 1] Step error: +10.0 (0x0A00)");
        error_in = 16'h0A00;  // +10.0

        repeat (100) begin
            @(posedge clk);
            cycle = cycle + 1;
            if (cycle <= 20 || cycle % 10 == 0) begin
                $display("  %5d | 0x%04h     | %8.4f   | 0x%04h     | 0x%04h     | %b    | %b%b",
                    cycle, error_in, q88_to_real(error_in),
                    pid_raw_out, pid_clamped_out, integrator_hold, pid_overflow, sat_overflow);
            end
        end

        // ---- TEST 2: Zero error (should see derivative kick, integral hold) ----
        $display("");
        $display("  [TEST 2] Step error to 0.0 (0x0000)");
        error_in = 16'h0000;

        repeat (100) begin
            @(posedge clk);
            cycle = cycle + 1;
            if (cycle <= 120 || cycle % 10 == 0) begin
                $display("  %5d | 0x%04h     | %8.4f   | 0x%04h     | 0x%04h     | %b    | %b%b",
                    cycle, error_in, q88_to_real(error_in),
                    pid_raw_out, pid_clamped_out, integrator_hold, pid_overflow, sat_overflow);
            end
        end

        // ---- TEST 3: Negative step error (-5.0 = 0xFB00) ----
        $display("");
        $display("  [TEST 3] Step error: -5.0 (0xFB00)");
        error_in = 16'hFB00;  // -5.0

        repeat (100) begin
            @(posedge clk);
            cycle = cycle + 1;
            if (cycle <= 220 || cycle % 10 == 0) begin
                $display("  %5d | 0x%04h     | %8.4f   | 0x%04h     | 0x%04h     | %b    | %b%b",
                    cycle, error_in, q88_to_real(error_in),
                    pid_raw_out, pid_clamped_out, integrator_hold, pid_overflow, sat_overflow);
            end
        end

        // ---- TEST 4: Large error to test saturation (+120.0 = 0x7800) ----
        $display("");
        $display("  [TEST 4] Large error: +120.0 (0x7800) — should saturate");
        error_in = 16'h7800;  // +120.0

        repeat (50) begin
            @(posedge clk);
            cycle = cycle + 1;
            $display("  %5d | 0x%04h     | %8.4f   | 0x%04h     | 0x%04h     | %b    | %b%b",
                cycle, error_in, q88_to_real(error_in),
                pid_raw_out, pid_clamped_out, integrator_hold, pid_overflow, sat_overflow);
            
            // Formal check during saturation test
            if (integrator_hold && !sat_overflow) begin
                $display("  [FAIL] Saturation occurred but sat_overflow flag is not set!");
                $fatal;
            end
        end

        // ---- TEST 5: Runtime gain change ----
        $display("");
        $display("  [TEST 5] Runtime gain change: Kp 1.0 → 2.0, error=+10.0");
        error_in = 16'h0A00;  // +10.0
        kp_reg   = 16'h0200;  // 2.0 in Q8.8

        repeat (20) begin
            @(posedge clk);
            cycle = cycle + 1;
            $display("  %5d | 0x%04h     | %8.4f   | 0x%04h     | 0x%04h     | %b    | %b%b  (Kp=%.4f)",
                cycle, error_in, q88_to_real(error_in),
                pid_raw_out, pid_clamped_out, integrator_hold, pid_overflow, sat_overflow,
                q88_to_real(kp_reg));
        end

        // ---- TEST 6: Reset mid-operation ----
        $display("");
        $display("  [TEST 6] Assert reset — all outputs should zero");
        rst = 1;
        repeat (3) @(posedge clk);
        cycle = cycle + 3;
        $display("  %5d | 0x%04h     | %8.4f   | 0x%04h     | 0x%04h     | %b    | %b%b",
            cycle, error_in, q88_to_real(error_in),
            pid_raw_out, pid_clamped_out, integrator_hold, pid_overflow, sat_overflow);

        // Verify reset behavior
        if (pid_raw_out == 16'h0000 && pid_clamped_out == 16'h0000)
            $display("  [PASS] Reset cleared PID output correctly.");
        else
            $display("  [FAIL] PID output not zero after reset! raw=0x%04h clamp=0x%04h",
                pid_raw_out, pid_clamped_out);

        rst = 0;

        // ---- Summary ----
        $display("");
        $display("============================================================");
        $display("  Testbench complete. Review tb_pid.vcd for waveforms.");
        $display("============================================================");
        $finish;
    end

endmodule

tb_pid.vcd
$date
	Thu May 14 20:00:05 2026
$end
$version
	Icarus Verilog
$end
$timescale
	1ps
$end
$scope module tb_pid $end
$var wire 1 ! sat_overflow $end
$var wire 16 " pid_raw_out [15:0] $end
$var wire 1 # pid_overflow $end
$var wire 16 $ pid_clamped_out [15:0] $end
$var wire 1 % integrator_hold $end
$var parameter 16 & KD_VAL $end
$var parameter 16 ' KI_VAL $end
$var parameter 16 ( KP_VAL $end
$var parameter 16 ) MAX_OUT $end
$var parameter 16 * MIN_OUT $end
$var reg 1 + clk $end
$var reg 16 , error_in [15:0] $end
$var reg 16 - kd_reg [15:0] $end
$var reg 16 . ki_reg [15:0] $end
$var reg 16 / kp_reg [15:0] $end
$var reg 1 0 rst $end
$var integer 32 1 cycle [31:0] $end
$scope function q88_to_real $end
$var reg 16 2 sval [15:0] $end
$var reg 16 3 val [15:0] $end
$upscope $end
$scope module dut_pid $end
$var wire 16 4 Kd [15:0] $end
$var wire 16 5 Ki [15:0] $end
$var wire 16 6 Kp [15:0] $end
$var wire 1 7 any_overflow $end
$var wire 1 + clk $end
$var wire 1 8 d_overflow $end
$var wire 1 9 diff_overflow $end
$var wire 16 : error_in [15:0] $end
$var wire 16 ; error_signed [15:0] $end
$var wire 1 < i_overflow $end
$var wire 1 = p_overflow $end
$var wire 1 0 rst $end
$var wire 1 > sum_overflow $end
$var wire 32 ? pid_sum_wide [31:0] $end
$var wire 16 @ pid_sum_clamped [15:0] $end
$var wire 16 A p_term [15:0] $end
$var wire 32 B p_product [31:0] $end
$var wire 1 % integrator_hold $end
$var wire 16 C i_term [15:0] $end
$var wire 32 D i_product [31:0] $end
$var wire 16 E i_increment [15:0] $end
$var wire 17 F error_diff_wide [16:0] $end
$var wire 16 G error_diff [15:0] $end
$var wire 16 H d_term [15:0] $end
$var wire 32 I d_product [31:0] $end
$var parameter 16 J MAX_OUT $end
$var parameter 16 K MIN_OUT $end
$var reg 32 L integrator [31:0] $end
$var reg 1 # overflow $end
$var reg 16 M pid_out [15:0] $end
$var reg 16 N prev_error [15:0] $end
$scope function clamp_diff $end
$var reg 17 O diff [16:0] $end
$upscope $end
$scope function clamp_integrator $end
$var reg 32 P acc [31:0] $end
$upscope $end
$scope function clamp_to_range $end
$var reg 16 Q max_val [15:0] $end
$var reg 16 R min_val [15:0] $end
$var reg 32 S val [31:0] $end
$upscope $end
$scope function saturate_q88 $end
$var reg 1 T overflow_neg $end
$var reg 1 U overflow_pos $end
$var reg 32 V product [31:0] $end
$var reg 16 W truncated [15:0] $end
$upscope $end
$upscope $end
$scope module dut_sat $end
$var wire 1 % integrator_hold $end
$var wire 1 ! overflow $end
$var wire 16 X raw_in [15:0] $end
$var wire 1 Y saturated_low $end
$var wire 1 Z saturated_high $end
$var wire 16 [ clamped_out [15:0] $end
$var parameter 16 \ MAX_OUT $end
$var parameter 16 ] MIN_OUT $end
$upscope $end
$upscope $end
$enddefinitions $end
$comment Show the parameter values. $end
$dumpall
b1000000100000000 ]
b111111100000000 \
b1000000100000000 K
b111111100000000 J
b1000000100000000 *
b111111100000000 )
b100000000 (
b11010 '
b10000000 &
$end
#0
$dumpvars
bx [
xZ
xY
bx X
bx W
bx V
xU
xT
bx S
b1000000100000000 R
b111111100000000 Q
bx P
bx O
bx N
bx M
bx L
bx I
bx H
bx G
bx F
b0 E
b0 D
bx C
b0 B
b0 A
bx @
bx ?
x>
0=
0<
b0 ;
b0 :
x9
x8
x7
b100000000 6
b11010 5
b10000000 4
b10000000 3
b10000000 2
b0 1
10
b100000000 /
b11010 .
b10000000 -
b0 ,
0+
x%
bx $
x#
bx "
x!
$end
#10000
07
08
b0 @
b0 S
0>
b0 ?
b0 H
0T
0U
b0 W
b0 V
b0 $
b0 [
0!
0%
b0 C
b0 P
b0 I
b0 G
b0 O
09
0#
0Z
0Y
b0 "
b0 M
b0 X
b0 L
b0 F
b0 N
1+
#20000
0+
#30000
1+
#40000
0+
#50000
1+
#60000
0+
#70000
1+
#80000
0+
#90000
b101000000000 N
b101000000000 @
b101000000000 S
b0 H
b101000000000 ?
b101000000000 A
b0 I
b0 G
b0 O
b100000100 E
b0 W
b0 V
b10100000000000000000 B
b0 F
b10000010000000000 D
b101000000000 ,
b101000000000 :
b101000000000 ;
00
1+
#100000
0+
#110000
b101000000000 $
b101000000000 [
b101100000100 @
b101100000100 S
b101100000100 ?
b100000100 C
b100000100 P
b101000000000 "
b101000000000 M
b101000000000 X
b100000100 L
b101000000000 2
b101000000000 3
b1 1
1+
#120000
0+
#130000
b101100000100 $
b101100000100 [
b110000001000 @
b110000001000 S
b110000001000 ?
b1000001000 C
b1000001000 P
b101100000100 "
b101100000100 M
b101100000100 X
b1000001000 L
b10 1
1+
#140000
0+
#150000
b110000001000 $
b110000001000 [
b110100001100 @
b110100001100 S
b110100001100 ?
b1100001100 C
b1100001100 P
b110000001000 "
b110000001000 M
b110000001000 X
b1100001100 L
b11 1
1+
#160000
0+
#170000
b110100001100 $
b110100001100 [
b111000010000 @
b111000010000 S
b111000010000 ?
b10000010000 C
b10000010000 P
b110100001100 "
b110100001100 M
b110100001100 X
b10000010000 L
b100 1
1+
#180000
0+
#190000
b111000010000 $
b111000010000 [
b111100010100 @
b111100010100 S
b111100010100 ?
b10100010100 C
b10100010100 P
b111000010000 "
b111000010000 M
b111000010000 X
b10100010100 L
b101 1
1+
#200000
0+
#210000
b111100010100 $
b111100010100 [
b1000000011000 @
b1000000011000 S
b1000000011000 ?
b11000011000 C
b11000011000 P
b111100010100 "
b111100010100 M
b111100010100 X
b11000011000 L
b110 1
1+
#220000
0+
#230000
b1000000011000 $
b1000000011000 [
b1000100011100 @
b1000100011100 S
b1000100011100 ?
b11100011100 C
b11100011100 P
b1000000011000 "
b1000000011000 M
b1000000011000 X
b11100011100 L
b111 1
1+
#240000
0+
#250000
b1000100011100 $
b1000100011100 [
b1001000100000 @
b1001000100000 S
b1001000100000 ?
b100000100000 C
b100000100000 P
b1000100011100 "
b1000100011100 M
b1000100011100 X
b100000100000 L
b1000 1
1+
#260000
0+
#270000
b1001000100000 $
b1001000100000 [
b1001100100100 @
b1001100100100 S
b1001100100100 ?
b100100100100 C
b100100100100 P
b1001000100000 "
b1001000100000 M
b1001000100000 X
b100100100100 L
b1001 1
1+
#280000
0+
#290000
b1001100100100 $
b1001100100100 [
b1010000101000 @
b1010000101000 S
b1010000101000 ?
b101000101000 C
b101000101000 P
b1001100100100 "
b1001100100100 M
b1001100100100 X
b101000101000 L
b1010 1
1+
#300000
0+
#310000
b1010000101000 $
b1010000101000 [
b1010100101100 @
b1010100101100 S
b1010100101100 ?
b101100101100 C
b101100101100 P
b1010000101000 "
b1010000101000 M
b1010000101000 X
b101100101100 L
b1011 1
1+
#320000
0+
#330000
b1010100101100 $
b1010100101100 [
b1011000110000 @
b1011000110000 S
b1011000110000 ?
b110000110000 C
b110000110000 P
b1010100101100 "
b1010100101100 M
b1010100101100 X
b110000110000 L
b1100 1
1+
#340000
0+
#350000
b1011000110000 $
b1011000110000 [
b1011100110100 @
b1011100110100 S
b1011100110100 ?
b110100110100 C
b110100110100 P
b1011000110000 "
b1011000110000 M
b1011000110000 X
b110100110100 L
b1101 1
1+
#360000
0+
#370000
b1011100110100 $
b1011100110100 [
b1100000111000 @
b1100000111000 S
b1100000111000 ?
b111000111000 C
b111000111000 P
b1011100110100 "
b1011100110100 M
b1011100110100 X
b111000111000 L
b1110 1
1+
#380000
0+
#390000
b1100000111000 $
b1100000111000 [
b1100100111100 @
b1100100111100 S
b1100100111100 ?
b111100111100 C
b111100111100 P
b1100000111000 "
b1100000111000 M
b1100000111000 X
b111100111100 L
b1111 1
1+
#400000
0+
#410000
b1100100111100 $
b1100100111100 [
b1101001000000 @
b1101001000000 S
b1101001000000 ?
b1000001000000 C
b1000001000000 P
b1100100111100 "
b1100100111100 M
b1100100111100 X
b1000001000000 L
b10000 1
1+
#420000
0+
#430000
b1101001000000 $
b1101001000000 [
b1101101000100 @
b1101101000100 S
b1101101000100 ?
b1000101000100 C
b1000101000100 P
b1101001000000 "
b1101001000000 M
b1101001000000 X
b1000101000100 L
b10001 1
1+
#440000
0+
#450000
b1101101000100 $
b1101101000100 [
b1110001001000 @
b1110001001000 S
b1110001001000 ?
b1001001001000 C
b1001001001000 P
b1101101000100 "
b1101101000100 M
b1101101000100 X
b1001001001000 L
b10010 1
1+
#460000
0+
#470000
b1110001001000 $
b1110001001000 [
b1110101001100 @
b1110101001100 S
b1110101001100 ?
b1001101001100 C
b1001101001100 P
b1110001001000 "
b1110001001000 M
b1110001001000 X
b1001101001100 L
b10011 1
1+
#480000
0+
#490000
b1110101001100 $
b1110101001100 [
b1111001010000 @
b1111001010000 S
b1111001010000 ?
b1010001010000 C
b1010001010000 P
b1110101001100 "
b1110101001100 M
b1110101001100 X
b1010001010000 L
b10100 1
1+
#500000
0+
#510000
b1111001010000 $
b1111001010000 [
b1111101010100 @
b1111101010100 S
b1111101010100 ?
b1010101010100 C
b1010101010100 P
b1111001010000 "
b1111001010000 M
b1111001010000 X
b1010101010100 L
b10101 1
1+
#520000
0+
#530000
b1111101010100 $
b1111101010100 [
b10000001011000 @
b10000001011000 S
b10000001011000 ?
b1011001011000 C
b1011001011000 P
b1111101010100 "
b1111101010100 M
b1111101010100 X
b1011001011000 L
b10110 1
1+
#540000
0+
#550000
b10000001011000 $
b10000001011000 [
b10000101011100 @
b10000101011100 S
b10000101011100 ?
b1011101011100 C
b1011101011100 P
b10000001011000 "
b10000001011000 M
b10000001011000 X
b1011101011100 L
b10111 1
1+
#560000
0+
#570000
b10000101011100 $
b10000101011100 [
b10001001100000 @
b10001001100000 S
b10001001100000 ?
b1100001100000 C
b1100001100000 P
b10000101011100 "
b10000101011100 M
b10000101011100 X
b1100001100000 L
b11000 1
1+
#580000
0+
#590000
b10001001100000 $
b10001001100000 [
b10001101100100 @
b10001101100100 S
b10001101100100 ?
b1100101100100 C
b1100101100100 P
b10001001100000 "
b10001001100000 M
b10001001100000 X
b1100101100100 L
b11001 1
1+
#600000
0+
#610000
b10001101100100 $
b10001101100100 [
b10010001101000 @
b10010001101000 S
b10010001101000 ?
b1101001101000 C
b1101001101000 P
b10001101100100 "
b10001101100100 M
b10001101100100 X
b1101001101000 L
b11010 1
1+
#620000
0+
#630000
b10010001101000 $
b10010001101000 [
b10010101101100 @
b10010101101100 S
b10010101101100 ?
b1101101101100 C
b1101101101100 P
b10010001101000 "
b10010001101000 M
b10010001101000 X
b1101101101100 L
b11011 1
1+
#640000
0+
#650000
b10010101101100 $
b10010101101100 [
b10011001110000 @
b10011001110000 S
b10011001110000 ?
b1110001110000 C
b1110001110000 P
b10010101101100 "
b10010101101100 M
b10010101101100 X
b1110001110000 L
b11100 1
1+
#660000
0+
#670000
b10011001110000 $
b10011001110000 [
b10011101110100 @
b10011101110100 S
b10011101110100 ?
b1110101110100 C
b1110101110100 P
b10011001110000 "
b10011001110000 M
b10011001110000 X
b1110101110100 L
b11101 1
1+
#680000
0+
#690000
b10011101110100 $
b10011101110100 [
b10100001111000 @
b10100001111000 S
b10100001111000 ?
b1111001111000 C
b1111001111000 P
b10011101110100 "
b10011101110100 M
b10011101110100 X
b1111001111000 L
b11110 1
1+
#700000
0+
#710000
b10100001111000 $
b10100001111000 [
b10100101111100 @
b10100101111100 S
b10100101111100 ?
b1111101111100 C
b1111101111100 P
b10100001111000 "
b10100001111000 M
b10100001111000 X
b1111101111100 L
b11111 1
1+
#720000
0+
#730000
b10100101111100 $
b10100101111100 [
b10101010000000 @
b10101010000000 S
b10101010000000 ?
b10000010000000 C
b10000010000000 P
b10100101111100 "
b10100101111100 M
b10100101111100 X
b10000010000000 L
b100000 1
1+
#740000
0+
#750000
b10101010000000 $
b10101010000000 [
b10101110000100 @
b10101110000100 S
b10101110000100 ?
b10000110000100 C
b10000110000100 P
b10101010000000 "
b10101010000000 M
b10101010000000 X
b10000110000100 L
b100001 1
1+
#760000
0+
#770000
b10101110000100 $
b10101110000100 [
b10110010001000 @
b10110010001000 S
b10110010001000 ?
b10001010001000 C
b10001010001000 P
b10101110000100 "
b10101110000100 M
b10101110000100 X
b10001010001000 L
b100010 1
1+
#780000
0+
#790000
b10110010001000 $
b10110010001000 [
b10110110001100 @
b10110110001100 S
b10110110001100 ?
b10001110001100 C
b10001110001100 P
b10110010001000 "
b10110010001000 M
b10110010001000 X
b10001110001100 L
b100011 1
1+
#800000
0+
#810000
b10110110001100 $
b10110110001100 [
b10111010010000 @
b10111010010000 S
b10111010010000 ?
b10010010010000 C
b10010010010000 P
b10110110001100 "
b10110110001100 M
b10110110001100 X
b10010010010000 L
b100100 1
1+
#820000
0+
#830000
b10111010010000 $
b10111010010000 [
b10111110010100 @
b10111110010100 S
b10111110010100 ?
b10010110010100 C
b10010110010100 P
b10111010010000 "
b10111010010000 M
b10111010010000 X
b10010110010100 L
b100101 1
1+
#840000
0+
#850000
b10111110010100 $
b10111110010100 [
b11000010011000 @
b11000010011000 S
b11000010011000 ?
b10011010011000 C
b10011010011000 P
b10111110010100 "
b10111110010100 M
b10111110010100 X
b10011010011000 L
b100110 1
1+
#860000
0+
#870000
b11000010011000 $
b11000010011000 [
b11000110011100 @
b11000110011100 S
b11000110011100 ?
b10011110011100 C
b10011110011100 P
b11000010011000 "
b11000010011000 M
b11000010011000 X
b10011110011100 L
b100111 1
1+
#880000
0+
#890000
b11000110011100 $
b11000110011100 [
b11001010100000 @
b11001010100000 S
b11001010100000 ?
b10100010100000 C
b10100010100000 P
b11000110011100 "
b11000110011100 M
b11000110011100 X
b10100010100000 L
b101000 1
1+
#900000
0+
#910000
b11001010100000 $
b11001010100000 [
b11001110100100 @
b11001110100100 S
b11001110100100 ?
b10100110100100 C
b10100110100100 P
b11001010100000 "
b11001010100000 M
b11001010100000 X
b10100110100100 L
b101001 1
1+
#920000
0+
#930000
b11001110100100 $
b11001110100100 [
b11010010101000 @
b11010010101000 S
b11010010101000 ?
b10101010101000 C
b10101010101000 P
b11001110100100 "
b11001110100100 M
b11001110100100 X
b10101010101000 L
b101010 1
1+
#940000
0+
#950000
b11010010101000 $
b11010010101000 [
b11010110101100 @
b11010110101100 S
b11010110101100 ?
b10101110101100 C
b10101110101100 P
b11010010101000 "
b11010010101000 M
b11010010101000 X
b10101110101100 L
b101011 1
1+
#960000
0+
#970000
b11010110101100 $
b11010110101100 [
b11011010110000 @
b11011010110000 S
b11011010110000 ?
b10110010110000 C
b10110010110000 P
b11010110101100 "
b11010110101100 M
b11010110101100 X
b10110010110000 L
b101100 1
1+
#980000
0+
#990000
b11011010110000 $
b11011010110000 [
b11011110110100 @
b11011110110100 S
b11011110110100 ?
b10110110110100 C
b10110110110100 P
b11011010110000 "
b11011010110000 M
b11011010110000 X
b10110110110100 L
b101101 1
1+
#1000000
0+
#1010000
b11011110110100 $
b11011110110100 [
b11100010111000 @
b11100010111000 S
b11100010111000 ?
b10111010111000 C
b10111010111000 P
b11011110110100 "
b11011110110100 M
b11011110110100 X
b10111010111000 L
b101110 1
1+
#1020000
0+
#1030000
b11100010111000 $
b11100010111000 [
b11100110111100 @
b11100110111100 S
b11100110111100 ?
b10111110111100 C
b10111110111100 P
b11100010111000 "
b11100010111000 M
b11100010111000 X
b10111110111100 L
b101111 1
1+
#1040000
0+
#1050000
b11100110111100 $
b11100110111100 [
b11101011000000 @
b11101011000000 S
b11101011000000 ?
b11000011000000 C
b11000011000000 P
b11100110111100 "
b11100110111100 M
b11100110111100 X
b11000011000000 L
b110000 1
1+
#1060000
0+
#1070000
b11101011000000 $
b11101011000000 [
b11101111000100 @
b11101111000100 S
b11101111000100 ?
b11000111000100 C
b11000111000100 P
b11101011000000 "
b11101011000000 M
b11101011000000 X
b11000111000100 L
b110001 1
1+
#1080000
0+
